{
"type": "FeatureCollection",
"name": "WSP",
"crs": { "type": "name", "properties": { "name": "urn:ogc:def:crs:OGC:1.3:CRS84" } },
"features": [
{ "type": "Feature", "properties": { "No": 1, "GND No.": 1102, "Name of the Tank": "Katukithula", "N": 7.089783, "E": 80.541383, "Observation": "There is a 3.0mx3.0mx2.0m(LxWxH)tank. Water is taken for  drinking", "Description": "Construction of a filtration tank (3.0m x2.0m x 1.2m) - For 25 families\n\n50mm dia PvC pipe in Solvent Socket Type in PNT11 - Water distribution\n\nTidying up\n\nContingencies (10%)", "Amount (Rs.)": 655600, "photopath": "https://raw.githubusercontent.com/MWS003-GIS/MWS003-GIS.github.io/main/IWWRMP/Data/EXD/200_photo/MWS_134_1/Katukithula water tank.jpg" }, "geometry": { "type": "Point", "coordinates": [ 80.541383, 7.089783 ] } },
{ "type": "Feature", "properties": { "No": 2, "GND No.": 1102, "Name of the Tank": "Shamrock", "N": 7.063398, "E": 80.529457, "Observation": "There is a 13m long 2.7 high anicut wall. It is part of 4m length is damage", "Description": "Construction of Concrete water storage tank of 20 cum ? size internal t 3mx3mx2.5\n\nInstall a filtration unit\n\n1:2:4 concrete with concrete mixer  (volume batching) - Construct damaged anicut wall\n\n75mm dia PvC pipe in Solvent Socket Type in PNT11 - Water", "Amount (Rs.)": 1206700, "photopath": "https://raw.githubusercontent.com/MWS003-GIS/MWS003-GIS.github.io/main/IWWRMP/Data/EXD/200_photo/MWS_134_1/Tank (2).jpg" }, "geometry": { "type": "Point", "coordinates": [ 80.529457, 7.063398 ] } },
{ "type": "Feature", "properties": { "No": 3, "GND No.": 1102, "Name of the Tank": "Katukithula", "N": 7.08988, "E": 80.547163, "Observation": "It is exists as a water source and jungle.", "Description": "Demarcate the boundaries and gazetting as a reserve the jungle and the water source\n\nContingencies (10%)", "Amount (Rs.)": 66000, "photopath": "https://raw.githubusercontent.com/MWS003-GIS/MWS003-GIS.github.io/main/IWWRMP/Data/EXD/200_photo/MWS_134_1/Katukithula.jpg" }, "geometry": { "type": "Point", "coordinates": [ 80.547163, 7.08988 ] } },
{ "type": "Feature", "properties": { "No": 4, "GND No.": 1103, "Name of the Tank": "Dhungha ella spring", "N": 7.06543, "E": 80.517641, "Observation": "It is exists as a water source and jungle. They dig holes and collect water through pipes.", "Description": "Construction of Concrete water storage tank of 20 cum ? size internal t 3mx3mx2.5\n\nInstall a filtration unit\n\nConstruction of Concrete anicut of  4.0 m length and height 0.9 m.\n\nClearing the site \n\nCommon excavation for foundation or quarry materials and", "Amount (Rs.)": 1266100, "photopath": "https://raw.githubusercontent.com/MWS003-GIS/MWS003-GIS.github.io/main/IWWRMP/Data/EXD/200_photo/MWS_134_1/Dhungaha ella spring.jpg" }, "geometry": { "type": "Point", "coordinates": [ 80.517641, 7.06543 ] } }
]
}
