{
"type": "FeatureCollection",
"name": "MT",
"crs": { "type": "name", "properties": { "name": "urn:ogc:def:crs:OGC:1.3:CRS84" } },
"features": [
{ "type": "Feature", "properties": { "No": 1, "MWS_ID": 83, "Name_of_Ta": "Angurawala Wewa", "Custodians": "DAD", "N": 7.246458, "E": 80.833722, "Remarks": "Desilting the tank and repairs to the sluice", "photopath": "https://raw.githubusercontent.com/MWS003-GIS/MWS003-GIS.github.io/main/IWWRMP/Data/EXD/200_photo/MWS_083/Anguruwala Lake 1.jpg" }, "geometry": { "type": "Point", "coordinates": [ 80.833722, 7.246458 ] } },
{ "type": "Feature", "properties": { "No": 2, "MWS_ID": 83, "Name_of_Ta": "Gonagalathenna Wewa", "Custodians": "DAD", "N": 7.234078, "E": 80.838082, "Remarks": "New tank and no repairs are needed.", "photopath": "https://raw.githubusercontent.com/MWS003-GIS/MWS003-GIS.github.io/main/IWWRMP/Data/EXD/200_photo/MWS_083/Gonawala Lake 1.jpg" }, "geometry": { "type": "Point", "coordinates": [ 80.838082, 7.234078 ] } },
{ "type": "Feature", "properties": { "No": 3, "MWS_ID": 83, "Name_of_Ta": "Ambagolla Kumbura", "Custodians": "DAD", "N": 7.221227, "E": 80.833475, "Remarks": "A new tank must be constructed at this location. According to information there had been a tank in this location.", "photopath": "https://raw.githubusercontent.com/MWS003-GIS/MWS003-GIS.github.io/main/IWWRMP/Data/EXD/200_photo/MWS_083/Dambagolla Lake.jpg" }, "geometry": { "type": "Point", "coordinates": [ 80.833475, 7.221227 ] } }
]
}
