{
"type": "FeatureCollection",
"name": "SR",
"crs": { "type": "name", "properties": { "name": "urn:ogc:def:crs:OGC:1.3:CRS84" } },
"features": [
{ "type": "Feature", "properties": { "No_": 1, "GND_No_": "60", "Descriptio": "Mathetilla Oya", "N": 6.866556, "E": 80.953216, "Observatio": "During the rainy season when too much water flows, Bank erosion occurs", "Descript_1": "Arrange stone packing-rubble packing-River bank\n\nVegetative cover improving along the river banks Areca nut seedling in 1.5m x 1.5m grid, Kumbuk/ Mee/ Godapara/ Kaduru/ Aththikka/ Wal Del/ Kekuna/ randomly mixed seedlings and planting at 3.5m x 3.5 m gri", "Amount": "715,000", "photopath": "https://raw.githubusercontent.com/MWS003-GIS/MWS003-GIS.github.io/main/IWWRMP/Data/EXD/200_photo/MWS_054/Mathetilla Oya.jpg" }, "geometry": { "type": "Point", "coordinates": [ 80.953216, 6.866556 ] } },
{ "type": "Feature", "properties": { "No_": 2, "GND_No_": "60A", "Descriptio": "Modaran Ulpatha Deniya", "N": 6.854846, "E": 80.926436, "Observatio": "Reserves have been set aside.", "Descript_1": "Remove unauthorized cultivation\n\nContingencies 10%", "Amount": "33,000", "photopath": "https://raw.githubusercontent.com/MWS003-GIS/MWS003-GIS.github.io/main/IWWRMP/Data/EXD/200_photo/MWS_054/Modaran Ulpatha Deniya.jpg" }, "geometry": { "type": "Point", "coordinates": [ 80.926436, 6.854846 ] } },
{ "type": "Feature", "properties": { "No_": 3, "GND_No_": "60D", "Descriptio": "Udowe canal", "N": 6.845865, "E": 80.938703, "Observatio": "Existing Earthen canal,  some places Constructed of rectangular concrete lining450mm x 450mm)   Water from this canal is used to grow paddy on an area of about 80 acres.", "Descript_1": "Construction of concrete canal\n\nSite preparation & setting out\n\nEarth excavation for foundation or quarry materials and haul the surplus materials up to 30m by Manually.\n\nPlywood form work including making, fixing & removing for concrete canals at ground", "Amount": "368,500", "photopath": "https://raw.githubusercontent.com/MWS003-GIS/MWS003-GIS.github.io/main/IWWRMP/Data/EXD/200_photo/MWS_054/Udowe canal.jpg" }, "geometry": { "type": "Point", "coordinates": [ 80.938703, 6.845865 ] } }
]
}
