{
"type": "FeatureCollection",
"name": "Landslides",
"crs": { "type": "name", "properties": { "name": "urn:ogc:def:crs:OGC:1.3:CRS84" } },
"features": [
{ "type": "Feature", "properties": { "No_": 3, "MWS_ID": 86, "GN_Divisio": 796, "GN_Divis_1": "Heeloya", "Land_Slide": "Landlide - Heeloya Watagala Road", "N": 7.324208, "E": 80.803766, "NBRO_Recom": "Needs NBRO concern", "Proposed_M": "Follow the recommendations of NBRO, having consulted", "photopath": "https://raw.githubusercontent.com/MWS003-GIS/MWS003-GIS.github.io/main/IWWRMP/Data/EXD/200_photo/MWS_086/IMG_20250423_104940 Landslide section of road.jpg" }, "geometry": { "type": "Point", "coordinates": [ 80.803766, 7.324208 ] } },
{ "type": "Feature", "properties": { "No_": 4, "MWS_ID": 86, "GN_Divisio": 796, "GN_Divis_1": "Heeloya", "Land_Slide": "Landlide - Heeloya Village Mr A.M. Kudabanda", "N": 7.321974, "E": 80.805396, "NBRO_Recom": "NBRO is aware", "Proposed_M": "Follow the recommendations of NBRO", "photopath": "https://raw.githubusercontent.com/MWS003-GIS/MWS003-GIS.github.io/main/IWWRMP/Data/EXD/200_photo/MWS_086/IMG_20250423_122743 Mr A.M Kudabanda Landslide land.jpg" }, "geometry": { "type": "Point", "coordinates": [ 80.805396, 7.321974 ] } },
{ "type": "Feature", "properties": { "No_": 5, "MWS_ID": 86, "GN_Divisio": 796, "GN_Divis_1": "Heeloya", "Land_Slide": "Landlide - Heeloya Village Mr R.G. Darmadasa", "N": 7.320192, "E": 80.801927, "NBRO_Recom": "NBRO is aware", "Proposed_M": "Follow the recommendations of NBRO", "photopath": "https://raw.githubusercontent.com/MWS003-GIS/MWS003-GIS.github.io/main/IWWRMP/Data/EXD/200_photo/MWS_086/IMG_20250423_112309 Mr R.G Darmadasa land Landslide.jpg" }, "geometry": { "type": "Point", "coordinates": [ 80.801927, 7.320192 ] } },
{ "type": "Feature", "properties": { "No_": 6, "MWS_ID": 86, "GN_Divisio": 798, "GN_Divis_1": "Kiribattalawa", "Land_Slide": "Landlide - From the Retiyagama main road to  Labuwagoda by-road", "N": 7.308896, "E": 80.801131, "NBRO_Recom": "Needs NBRO concern", "Proposed_M": "Follow the recommendations of NBRO, having consulted", "photopath": "https://raw.githubusercontent.com/MWS003-GIS/MWS003-GIS.github.io/main/IWWRMP/Data/EXD/200_photo/MWS_086/IMG_20250425_102624Retiyagama Earth slip.jpg" }, "geometry": { "type": "Point", "coordinates": [ 80.801131, 7.308896 ] } }
]
}
