{
"type": "FeatureCollection",
"name": "SR",
"crs": { "type": "name", "properties": { "name": "urn:ogc:def:crs:OGC:1.3:CRS84" } },
"features": [
{ "type": "Feature", "properties": { "No": 1, "MWS_ID": 80, "GND_No_": 852, "Name_of_th": "Pallewela Oya", "N": 7.299527, "E": 80.886532, "Observatio": "During the rainy season when too much water flows, Bank erosion occurs", "Descriptio": "Arrange stone packing-rubble packing\n\nVegetative cover improving around structures (5m x 10m) with Areca nut seedling in 1.5m x \n1.5m grid, Kumbuk/ Mee/ Godapara/ Kaduru/ Aththikka/ Wal Del/ Kekuna/ randomly mixed \nseedlings and planting at 3.5m x 3.5 m", "Amount": "392,700", "photopath": "https://raw.githubusercontent.com/MWS003-GIS/MWS003-GIS.github.io/main/IWWRMP/Data/EXD/200_photo/MWS_080/IMG_20250603_095449 Pallewela oya.jpg" }, "geometry": { "type": "Point", "coordinates": [ 80.886532, 7.299527 ] } },
{ "type": "Feature", "properties": { "No": 2, "MWS_ID": 80, "GND_No_": 858, "Name_of_th": "Radamana kandura", "N": 7.266464, "E": 80.888801, "Observatio": "During the rainy season when too much water flows, Bank erosion occurs", "Descriptio": "Arrange stone packing-rubble packing\n\nVegetative cover improving around structures (5m x 10m) with Areca nut seedling in 1.5m x \n1.5m grid, Kumbuk/ Mee/ Godapara/ Kaduru/ Aththikka/ Wal Del/ Kekuna/ randomly mixed \nseedlings and planting at 3.5m x 3.5 m", "Amount": "573,100", "photopath": "https://raw.githubusercontent.com/MWS003-GIS/MWS003-GIS.github.io/main/IWWRMP/Data/EXD/200_photo/MWS_080/IMG_20250620_121939 Radamanna lidakotuwe Anicut.jpg" }, "geometry": { "type": "Point", "coordinates": [ 80.888801, 7.266464 ] } },
{ "type": "Feature", "properties": { "No": 3, "MWS_ID": 80, "GND_No_": 859, "Name_of_th": "Canal near the clinic center", "N": 7.261316, "E": 80.88786, "Observatio": "During the rainy season when too much water flows, Bank erosion occurs", "Descriptio": "Arrange stone packing-rubble packing\n\nVegetative cover improving around structures (5m x 10m) with Areca nut seedling in 1.5m x \n1.5m grid, Kumbuk/ Mee/ Godapara/ Kaduru/ Aththikka/ Wal Del/ Kekuna/ randomly mixed \nseedlings and planting at 3.5m x 3.5 m", "Amount": "524,291", "photopath": "https://raw.githubusercontent.com/MWS003-GIS/MWS003-GIS.github.io/main/IWWRMP/Data/EXD/200_photo/MWS_080/IMG_20250612_144216 Thotupala canal.jpg" }, "geometry": { "type": "Point", "coordinates": [ 80.88786, 7.261316 ] } }
]
}
