{
"type": "FeatureCollection",
"name": "WSP",
"crs": { "type": "name", "properties": { "name": "urn:ogc:def:crs:OGC:1.3:CRS84" } },
"features": [
{ "type": "Feature", "properties": { "No": 1, "MWS_ID": 82, "GND_No_": 860, "Name_of_Sp": "Pihillagaha Madiththa Linda (spring)", "N": 7.258054, "E": 80.882085, "Observatio": "The  Well is constructed (4.4 m x 4.4 m x6.0 m, L*W*H). A well  Located on Peellagahamadiththa small lake .used for drinking and bathing.", "Descriptio": "Wet Silt removing from Canal or Tank beds and haul the surplus materials up to 1.6 km distance by machinery.(This rate is excluding of transporting of machinery)-lake\n\nMiscellaneous\n\n Contingencies (10%)", "Amount": "7,150.00", "photopath": "https://raw.githubusercontent.com/MWS003-GIS/MWS003-GIS.github.io/main/IWWRMP/Data/EXD/200_photo/MWS_082/IMG_20250612_114644 Peella gahamadiththa well.jpg" }, "geometry": { "type": "Point", "coordinates": [ 80.882085, 7.258054 ] } }
]
}
