{
"type": "FeatureCollection",
"name": "DWS",
"crs": { "type": "name", "properties": { "name": "urn:ogc:def:crs:OGC:1.3:CRS84" } },
"features": [
{ "type": "Feature", "properties": { "No": 10, "GND No.": 474, "Scheme": "Kandamulla Village- Located in Palalgolla GN", "N": 7.046311, "E": 80.697829, "Observation": "The  Water stock tank is constructed (15 m 3   Ferrow cement tank)", "Description": "Improvements to Kandamulla Community Water Supply Project \n\nSupplying & laying 40mm Dia PVC pipe line in solvent socket type in PN-11 rate including socket, solvent cement, etc.\n\nMiscellaneous\n\nContingancies 10%", "Amount (Rs.)": 308000, "photopath": "https://raw.githubusercontent.com/MWS003-GIS/MWS003-GIS.github.io/main/IWWRMP/Data/EXD/200_photo/MWS_174/-" }, "geometry": { "type": "Point", "coordinates": [ 80.697829, 7.046311 ] } }
]
}
