{
"type": "FeatureCollection",
"name": "DWS",
"crs": { "type": "name", "properties": { "name": "urn:ogc:def:crs:OGC:1.3:CRS84" } },
"features": [
{ "type": "Feature", "properties": { "No": 1, "GND No.": 1173, "Name of Sp": "Gramhill Colony", "N": 7.151581, "E": 80.609558, "Observatio": "A well has been built to collect spring water (Dia.=5.0m, H=6.0m). There is stock tank and filtering system. It is a well-functioning water scheme. There are no boundaries. Villagers request construction of another stock tank (20000L) to further expand w", "Descriptio": "Construction of Concrete water storage tank of 20 cum - size internal t 3mx3mx2.5/Vegetative cover improving around structures (5m x 10m) with planting Arecanut seedling in 1.5m x 1.5m grid, and planting Kumbuk/ Mee/ Godapara/ Kaduru/ Aththikka/ Wal Del/", "Amount (Rs": "863,500.00", "photopath": "https://raw.githubusercontent.com/MWS003-GIS/MWS003-GIS.github.io/main/IWWRMP/Data/EXD/200_photo/MWS_124_2/Drinking_Water_Sources_to_be_Conserved-Kirimetiya.jpg" }, "geometry": { "type": "Point", "coordinates": [ 80.609558, 7.151581 ] } },
{ "type": "Feature", "properties": { "No": 2, "GND No.": 1181, "Name of Sp": "Pupuressa", "N": 7.131697, "E": 80.667121, "Observatio": "A dam and catchpit is built across a flowing water stream to collect water(L=1.0m, W=1.0m, H=0.6m). A formal water scheme has been established. The boundaries are not marked.", "Descriptio": "Vegetative cover improving around structures (5m x 10m) with planting Arecanut seedling in 1.5m x 1.5m grid, and planting Kumbuk/ Mee/ Godapara/ Kaduru/ Aththikka/ Wal Del/ Kekuna/ randomly mixed seedlings in 3.5m x 3.5 m grid/Miscellaneous/CONTINGANCIES", "Amount (Rs": "304,700.00", "photopath": "https://raw.githubusercontent.com/MWS003-GIS/MWS003-GIS.github.io/main/IWWRMP/Data/EXD/200_photo/MWS_124_2/New_Water_Projects-Water_Stok_Tank-Pupuressa_Upper_Division (2).jpg" }, "geometry": { "type": "Point", "coordinates": [ 80.667121, 7.131697 ] } },
{ "type": "Feature", "properties": { "No": 3, "GND No.": 1181, "Name of Sp": "Pupuressa", "N": 7.116805, "E": 80.678575, "Observatio": "A  catchpit is built across a flowing water stream to collect water(L=5.75m, W=3.75m, H=3.0m). A Stock tank has been constructed using RRM (L=2.0m, W=1.0m, H=0.6m) and the top is covered with a concrete slab.  Water is leaking from the well and the bound", "Descriptio": "Construction of curtain wall (0.075mm thk) with 1:2:4 (3/4\") concrete, 1/2\" dowels at 600mm x 600mm intervals and embedded with chicken mesh/Miscellaneous/Contingencies 10%", "Amount (Rs": "38,500.00", "photopath": "https://raw.githubusercontent.com/MWS003-GIS/MWS003-GIS.github.io/main/IWWRMP/Data/EXD/200_photo/MWS_124_2/Pupuressa_Estate_Midle_Division_water_Scheme_Stock_Tanks (2).jpg" }, "geometry": { "type": "Point", "coordinates": [ 80.678575, 7.116805 ] } }
]
}
