{
"type": "FeatureCollection",
"name": "MI",
"crs": { "type": "name", "properties": { "name": "urn:ogc:def:crs:OGC:1.3:CRS84" } },
"features": [
{ "type": "Feature", "properties": { "No": 1, "GND No.": 1173, "Name of th": "Mahara wela raja ela canal", "N": 7.152694, "E": 80.62017, "Observatio": "The anicut is in good condition. The total length of canal is 2.5Km. Although some parts of the canal have been concreted, some parts of it have fallen in to disrepair (W=0.6m and, H=0.45m). There is still about 1.5Km to be concreted. 108 Acres of paddy", "Descriptio": "Canals reservation protection by concrete lining  For  125mm thick , 0.5m  wide  and 0.4m high canal -double banking/Stream / canal  reservation protection by earthfilling of  strip   of 1.5m to 2m wide  and average Depth of 0.5m/Vegetative cover improvi", "Amount (Rs": "4,983,000.00", "field_9": "Construction of 1.5 m high Weir across stream / river excluding abutments and stop planks/Construction of 1.8m high 1:3:6 (40mm) cement concrete Retaining Wall /75mm tk. Stop planks (kumbuk ) with 10mm dia. 2nos. M. S. Iron hooks and applies 2 coats of h" }, "geometry": { "type": "Point", "coordinates": [ 80.62017, 7.152694 ] } },
{ "type": "Feature", "properties": { "No": 2, "GND No.": 1181, "Name of th": "Parana pattiya anicut", "N": 7.125662, "E": 80.66219, "Observatio": "Located in atabage oya. The canal and the anicut have been completely destroyed.", "Descriptio": "Construction of 1.5 m high Weir across stream / river excluding abutments and stop planks/Construction of 1.8m high 1:3:6 (40mm) cement concrete Retaining Wall /75mm tk. Stop planks (kumbuk ) with 10mm dia. 2nos. M. S. Iron hooks and applies 2 coats of h", "Amount (Rs": "4,873,000.00", "field_9": null }, "geometry": { "type": "Point", "coordinates": [ 80.66219, 7.125662 ] } }
]
}
