{
"type": "FeatureCollection",
"name": "SR",
"crs": { "type": "name", "properties": { "name": "urn:ogc:def:crs:OGC:1.3:CRS84" } },
"features": [
{ "type": "Feature", "properties": { "No": 1, "GND No.": 1173, "Name of Sp": "Atabage oya (egodamaga)", "N": 7.149527, "E": 80.617894, "Observatio": "There are large trees at some places on both sides of the bank. But banks are eroded. Too much water flows in rainy season. In some places, small amounts of garbage have been dumped into streams, and in some places, reserved lands are being misused.", "Descriptio": "Dry rubble packing (rubble size over 225mm) boulders locally found/Vegetative cover improving around structures (5m x 10m) with planting Arecanut seedling in 1.5m x 1.5m grid, and planting Kumbuk/ Mee/ Godapara/ Kaduru/ Aththikka/ Wal Del/ Kekuna/ random", "Amount (Rs": "2,530,000.00" }, "geometry": { "type": "Point", "coordinates": [ 80.617894, 7.149527 ] } },
{ "type": "Feature", "properties": { "No": 2, "GND No.": 1182, "Name of Sp": "Atabage Oya", "N": 7.145351, "E": 80.640969, "Observatio": "There are large trees at some places on both sides of the bank. But banks are eroded. Too much water flows in rainy season. In some places, small amounts of garbage have been dumped into streams, and in some places, reserved lands are being misused.", "Descriptio": "Dry rubble packing (rubble size over 225mm) boulders locally found/Vegetative cover improving for narrow strips (1.5m-2.0m wide) with Arecanut seedlings at 1.5m spacing in 2 rows, Betel plants VP at 3m spacing in 1 row, Green gram as a cover crop/Miscell", "Amount (Rs": "1,116,500.00" }, "geometry": { "type": "Point", "coordinates": [ 80.640969, 7.145351 ] } },
{ "type": "Feature", "properties": { "No": 3, "GND No.": 1181, "Name of Sp": "Paranapattiya Waterfall", "N": 7.128716, "E": 80.66285, "Observatio": "There are large trees at some places on both sides of the bank. But banks are eroded. Too much water flows in rainy season. In some places, small amounts of garbage have been dumped into streams, and in some places, reserved lands are being misused.", "Descriptio": "Dry rubble packing (rubble size over 225mm) boulders locally found/Vegetative cover improving for narrow strips (1.5m-2.0m wide) with Arecanut seedlings at 1.5m spacing in 2 rows, Betel plants VP at 3m spacing in 1 row, Green gram as a cover crop/Miscell", "Amount (Rs": "638,000.00" }, "geometry": { "type": "Point", "coordinates": [ 80.66285, 7.128716 ] } },
{ "type": "Feature", "properties": { "No": 4, "GND No.": 1181, "Name of Sp": "Gigirana 0ya", "N": 7.129789, "E": 80.66412, "Observatio": "There are large trees at some places on both sides of the bank. But banks are eroded. Too much water flows in rainy season. In some places, small amounts of garbage have been dumped into streams, and in some places, reserved lands are being misused.", "Descriptio": "Dry rubble packing (rubble size over 225mm) boulders locally found/Vegetative cover improving for narrow strips (1.5m-2.0m wide) with Arecanut seedlings at 1.5m spacing in 2 rows, Betel plants VP at 3m spacing in 1 row, Green gram as a cover crop/Miscell", "Amount (Rs": "1,034,000.00" }, "geometry": { "type": "Point", "coordinates": [ 80.66412, 7.129789 ] } },
{ "type": "Feature", "properties": { "No": 5, "GND No.": 1181, "Name of Sp": "Atabage oya", "N": 7.126512, "E": 80.66194, "Observatio": "There are large trees at some places on both sides of the bank. But banks are eroded. Too much water flows in rainy season. In some places, small amounts of garbage have been dumped into streams, and in some places, reserved lands are being misused.", "Descriptio": "Dry rubble packing (rubble size over 225mm) boulders locally found/Vegetative cover improving for narrow strips (1.5m-2.0m wide) with Arecanut seedlings at 1.5m spacing in 2 rows, Betel plants VP at 3m spacing in 1 row, Green gram as a cover crop/Miscell", "Amount (Rs": "583,000.00" }, "geometry": { "type": "Point", "coordinates": [ 80.66194, 7.126512 ] } },
{ "type": "Feature", "properties": { "No": 6, "GND No.": 1183, "Name of Sp": "Kachamale Oya", "N": 7.103044, "E": 80.681595, "Observatio": "There are large trees at some places on both sides of the bank. But banks are eroded. Too much water flows in rainy season. In some places, small amounts of garbage have been dumped into streams, and in some places, reserved lands are being misused.", "Descriptio": "Dry rubble packing (rubble size over 225mm) boulders locally found/Vegetative cover improving for narrow strips (1.5m-2.0m wide) with Arecanut seedlings at 1.5m spacing in 2 rows, Betel plants VP at 3m spacing in 1 row, Green gram as a cover crop/Miscell", "Amount (Rs": "693,000.00" }, "geometry": { "type": "Point", "coordinates": [ 80.681595, 7.103044 ] } }
]
}
