{
"type": "FeatureCollection",
"name": "MI",
"crs": { "type": "name", "properties": { "name": "urn:ogc:def:crs:OGC:1.3:CRS84" } },
"features": [
{ "type": "Feature", "properties": { "No": 1, "MWS_ID": 132, "GND_No_": 1187, "Name_of_th": "Anicut and Canal of Mahakumbura Yaaya", "N": 7.093564, "E": 80.575279, "Observatio": "Although the anicut is in good condition, it is unable to collect water due to bank erosion. The canal has also been developed. 6 acres of paddy is cultivated from this canal.", "Descriptio": "Extension of the existing anicut by 1.50 m length,  0.75 m height and minor repairs to the existing anicut\n\nClearing the site and scarifying the surfaces of the existing anicut\n\nCommon excavation for foundation or quarry materials and haul the surplus up", "Amount__Rs": "266,200", "photopath": "https://raw.githubusercontent.com/MWS003-GIS/MWS003-GIS.github.io/main/IWWRMP/Data/EXD/200_photo/MWS_132/Minor Irrigation - Mahakumbura Yaaya Canal and anicut (4).jpg" }, "geometry": { "type": "Point", "coordinates": [ 80.575279, 7.093564 ] } }
]
}
