{
"type": "FeatureCollection",
"name": "DWS",
"crs": { "type": "name", "properties": { "name": "urn:ogc:def:crs:OGC:1.3:CRS84" } },
"features": [
{ "type": "Feature", "properties": { "No": 1, "MWS_ID": 47, "GND_No_": "42", "Name_of_th": "-", "N": 6.967899, "E": 80.89965, "Observatio": "A water storage tank has been constructed that is 4.4m long, 4.4m wide and 5.0m deep. The tank is leaking water in some places. About 115 families use water. Water should be purified. The water distribution system is in dilapidated condition.", "Descriptio": "Repairs to the existing storage tanks\n\nScarifying existing or concrete surface \n\nPlaster 12mm thick in 1:3 cement and sand finished smooth with gray cement floating\n\nWater proofing with cementitious water proofing agent approved by the Engineer, (Thor se", "Amount": "3,391,300", "photopath": "-" }, "geometry": { "type": "Point", "coordinates": [ 80.89965, 6.967899 ] } },
{ "type": "Feature", "properties": { "No": 2, "MWS_ID": 47, "GND_No_": "42", "Name_of_th": "-", "N": 6.966654, "E": 80.89785, "Observatio": "A water tank is constructed using concrete rings. About 70 families use water. Water should be purified. The water distribution system is in dilapidated condition.", "Descriptio": "Construction of the water Transmission line\n\nExcavation in trenches less than 300mm width in normal earth average depth of not exceeding 1.0m from ground level inclusive of back filling, compacting and disposal of surplus earth for the transmission line", "Amount": "2,081,200", "photopath": "-" }, "geometry": { "type": "Point", "coordinates": [ 80.89785, 6.966654 ] } },
{ "type": "Feature", "properties": { "No": 3, "MWS_ID": 47, "GND_No_": "42", "Name_of_th": "-", "N": 6.958965, "E": 80.90066, "Observatio": "Currently, a concrete pit has been constructed and PVC pipe used to supply drinking water to about 12 families. The water is in very dirty condition. A water storage tank has been constructed at a low location and is in a completely dilapidated condition", "Descriptio": "Construction of the water tank & Filtering arrangement \n\nConstruction of 1.0 m x 1.0 m x 1.5 m (LxWxH) filter tank with necessary parts\n\nProviding the filter media\n\nConstruction of Concrete water storage tank of 20 cum - size internal t 3mx3mx2.5\n\nMiscel", "Amount": "1,245,200", "photopath": "-" }, "geometry": { "type": "Point", "coordinates": [ 80.90066, 6.958965 ] } },
{ "type": "Feature", "properties": { "No": 4, "MWS_ID": 47, "GND_No_": "42B", "Name_of_th": "Wasanagama - Haputhalewela", "N": 6.977755, "E": 80.91056, "Observatio": "Currently, a concrete pit has been constructed and PVC pipe used to supply drinking water to about 40 families. The water is in very dirty condition.", "Descriptio": "Construction of Filter tank\n\nConstruction of 1.0 m x 1.0 m x 1.5 m (LxWxH) filter tank with necessary parts\n\nProviding the filter media\n\nMiscellaneous\n\nContingencies 10%", "Amount": "79,200", "photopath": "https://raw.githubusercontent.com/MWS003-GIS/MWS003-GIS.github.io/main/IWWRMP/Data/EXD/200_photo/MWS_047/Haputalewela Canal 2.jpg" }, "geometry": { "type": "Point", "coordinates": [ 80.91056, 6.977755 ] } },
{ "type": "Feature", "properties": { "No": 5, "MWS_ID": 47, "GND_No_": "42B", "Name_of_th": "Alagolla Tea Factory area", "N": 6.984784, "E": 80.92651, "Observatio": "A water tank is constructed using concrete rings and water is distributed through it for about 40 families. The water is in very dirty condition.", "Descriptio": "Construction of Filter tank\n\nConstruction of 1.0 m x 1.0 m x 1.5 m (LxWxH) filter tank with necessary parts\n\nProviding the filter media\n\nMiscellaneous\n\nContingencies 10%", "Amount": "79,200", "photopath": "-" }, "geometry": { "type": "Point", "coordinates": [ 80.92651, 6.984784 ] } }
]
}
