{
"type": "FeatureCollection",
"name": "WSP",
"crs": { "type": "name", "properties": { "name": "urn:ogc:def:crs:OGC:1.3:CRS84" } },
"features": [
{ "type": "Feature", "properties": { "No": 50, "GND No.": "475E", "Name of the Tank": "Midelton Estate (50 Ha)", "N": 6.933166, "E": 80.661428, "Observation": "120 families use this water. They used muddy water for drinking purposes. having  a 4*4 tank.", "Description": "Construction of a Water Stock Tank (3m x3m x 1m)\n\nSite?preparation?&?setting?out\n\nPlywood form work including making, fixing & removing for structure ?05 uses\n\nCutting, Bending & Placing tor steel reinforcement bars\n\n1:2:4 concrete with concrete mixer  (", "Amount (Rs.)": 961400, "photopath": "-" }, "geometry": { "type": "Point", "coordinates": [ 80.661428, 6.933166 ] } },
{ "type": "Feature", "properties": { "No": 51, "GND No.": "475F", "Name of the Tank": "Logie estate", "N": 6.921661, "E": 80.675041, "Observation": "This waterline has not been used for 10 years.  Having a 4*4 tank and no pipeline from this tank.  370 families used this waterline.", "Description": "Construction of a Water Stock Tank (3m x3m x 1m)\n\nSite?preparation?&?setting?out\n\nPlywood form work including making, fixing & removing for structure ?05 uses\n\nCutting, Bending & Placing tor steel reinforcement bars\n\n1:2:4 concrete with concrete mixer  (", "Amount (Rs.)": 1236400, "photopath": "https://raw.githubusercontent.com/MWS003-GIS/MWS003-GIS.github.io/main/IWWRMP/Data/EXD/200_photo/MWS_154/logie estate (2).jpeg" }, "geometry": { "type": "Point", "coordinates": [ 80.675041, 6.921661 ] } },
{ "type": "Feature", "properties": { "No": 52, "GND No.": "475R", "Name of the Tank": "Glanamera", "N": 6.919732, "E": 80.656754, "Observation": "No proper covering and no water pump to pump water , pump house and other facilities are available", "Description": "Fabricating?&?fixing?security?weld?mesh?in?open type?buildings?in?GI?weld?mesh?50mm?x?50mmSWG?10,?welded?on?40mm?x?40mm?x?5mm? angle?frame?complete?with?application?of?two coats?enamel?paint?over?two?coats?of? anticorrosive?paint?and?complete. All?as?per", "Amount (Rs.)": 407000, "photopath": "https://raw.githubusercontent.com/MWS003-GIS/MWS003-GIS.github.io/main/IWWRMP/Data/EXD/200_photo/MWS_154/Glanamera tank.jpg" }, "geometry": { "type": "Point", "coordinates": [ 80.656754, 6.919732 ] } },
{ "type": "Feature", "properties": { "No": 53, "GND No.": "475R", "Name of the Tank": "Katukelle", "N": 6.930043, "E": 80.648449, "Observation": "there is existing tank but its not enough", "Description": "Construction of a Water Stock Tank (2.5m x2.5m x 2m)\n\nSite?preparation?&?setting?out\n\nPlywood form work including making, fixing & removing for structure ?05 uses\n\nCutting, Bending & Placing tor steel reinforcement bars\n\n1:2:4 concrete with concrete mixe", "Amount (Rs.)": 772200, "photopath": "https://raw.githubusercontent.com/MWS003-GIS/MWS003-GIS.github.io/main/IWWRMP/Data/EXD/200_photo/MWS_154/Katukelle.jpg" }, "geometry": { "type": "Point", "coordinates": [ 80.648449, 6.930043 ] } }
]
}
