{
"type": "FeatureCollection",
"name": "Landslides",
"crs": { "type": "name", "properties": { "name": "urn:ogc:def:crs:OGC:1.3:CRS84" } },
"features": [
{ "type": "Feature", "properties": { "No.": 4, "GN Divisio": 1137, "GN Divis_1": "Nillamba", "Land Slide": "High risk area - Nillamba Ihala village", "N": 7.19776, "E": 80.637365, "NBRO Recom": "NBRO is aware", "Proposed M": "Follow the recommendations of NBRO", "photopath": "https://raw.githubusercontent.com/MWS003-GIS/MWS003-GIS.github.io/main/IWWRMP/Data/EXD/200_photo/MWS_127_1/Disaster-Nillamba Ihala village (2).jpg" }, "geometry": { "type": "Point", "coordinates": [ 80.637365, 7.19776 ] } },
{ "type": "Feature", "properties": { "No.": 6, "GN Divisio": 1158, "GN Divis_1": "Ganegoda", "Land Slide": "Landsliding - Dankele of Illagolla division", "N": 7.200509, "E": 80.61533, "NBRO Recom": "NBRO is aware", "Proposed M": "Follow the recommendations of NBRO", "photopath": "https://raw.githubusercontent.com/MWS003-GIS/MWS003-GIS.github.io/main/IWWRMP/Data/EXD/200_photo/MWS_127_1/Disaster_Illagolla_Dankele_Landslide_Risk_Area.jpg" }, "geometry": { "type": "Point", "coordinates": [ 80.61533, 7.200509 ] } },
{ "type": "Feature", "properties": { "No.": 3, "GN Divisio": 1160, "GN Divis_1": "Haloya", "Land Slide": "Bank collapsing - Both sides of the Haloya main road", "N": 7.208905, "E": 80.621214, "NBRO Recom": "Needs NBRO concern", "Proposed M": "Taking appropriate action on the recommendations of NBRO", "photopath": "https://raw.githubusercontent.com/MWS003-GIS/MWS003-GIS.github.io/main/IWWRMP/Data/EXD/200_photo/MWS_127_1/Disaster-Landslide.jpg" }, "geometry": { "type": "Point", "coordinates": [ 80.621214, 7.208905 ] } },
{ "type": "Feature", "properties": { "No.": 5, "GN Divisio": 1162, "GN Divis_1": "Galoya", "Land Slide": "The house has been damaged, with cracked walls and sinking foundations - Mr. rajarathnam Selvarathnam's house", "N": 7.210763, "E": 80.615562, "NBRO Recom": "NBRO is aware", "Proposed M": "Follow the recommendations of NBRO", "photopath": "https://raw.githubusercontent.com/MWS003-GIS/MWS003-GIS.github.io/main/IWWRMP/Data/EXD/200_photo/MWS_127_1/Disaster_Mr.Rajarathnam's_Home.jpg" }, "geometry": { "type": "Point", "coordinates": [ 80.615562, 7.210763 ] } }
]
}
