{
"type": "FeatureCollection",
"name": "Landslides",
"crs": { "type": "name", "properties": { "name": "urn:ogc:def:crs:OGC:1.3:CRS84" } },
"features": [
{ "type": "Feature", "properties": { "No.": 3, "GN Divisio": 1160, "GN Divis_1": "Haloya", "Land Slide": "Bank collapsing - Both sides of the Haloya main road", "N or X": 7.208905, "E or Y": 80.621214, "NBRO Recom": "Needs NBRO concern", "Proposed M": "Taking appropriate action on the recommendations of NBRO" }, "geometry": { "type": "Point", "coordinates": [ 80.621214, 7.208905 ] } },
{ "type": "Feature", "properties": { "No.": 4, "GN Divisio": 1137, "GN Divis_1": "Nillamba", "Land Slide": "High risk area - Nillamba Ihala village", "N or X": 7.19776, "E or Y": 80.637365, "NBRO Recom": "NBRO is aware", "Proposed M": "Follow the recommendations of NBRO" }, "geometry": { "type": "Point", "coordinates": [ 80.637365, 7.19776 ] } },
{ "type": "Feature", "properties": { "No.": 5, "GN Divisio": 1162, "GN Divis_1": "Galoya", "Land Slide": "The house has been damaged, with cracked walls and sinking foundations - Mr. rajarathnam Selvarathnam's house", "N or X": 7.210763, "E or Y": 80.615562, "NBRO Recom": "NBRO is aware", "Proposed M": "Follow the recommendations of NBRO" }, "geometry": { "type": "Point", "coordinates": [ 80.615562, 7.210763 ] } },
{ "type": "Feature", "properties": { "No.": 6, "GN Divisio": 1158, "GN Divis_1": "Ganegoda", "Land Slide": "Landsliding - Dankele of Illagolla division", "N or X": 7.200509, "E or Y": 80.61533, "NBRO Recom": "NBRO is aware", "Proposed M": "Follow the recommendations of NBRO" }, "geometry": { "type": "Point", "coordinates": [ 80.61533, 7.200509 ] } }
]
}
