{
"type": "FeatureCollection",
"name": "MT",
"crs": { "type": "name", "properties": { "name": "urn:ogc:def:crs:OGC:1.3:CRS84" } },
"features": [
{ "type": "Feature", "properties": { "Name_of_Tank": "Minor tank near the community hall of Pahala Gorakaoya", "Custodians": "DAD", "N": 7.068605, "E": 80.562479, "Remarks": "Desilting and Replacement of the sluice door with accessories.", "photopath": "https://raw.githubusercontent.com/MWS003-GIS/MWS003-GIS.github.io/main/IWWRMP/Data/EXD/200_photo/MWS_178/IMG_20251028_102840.jpg" }, "geometry": { "type": "Point", "coordinates": [ 80.562479, 7.068605 ] } }
]
}
