{
"type": "FeatureCollection",
"name": "Landslides",
"crs": { "type": "name", "properties": { "name": "urn:ogc:def:crs:OGC:1.3:CRS84" } },
"features": [
{ "type": "Feature", "properties": { "No.": 3, "GN Division No.": 477, "GN Division": "Pattipola", "Landslides": "High Wind - Sirisamangama", "N": 6.857913, "E": 80.828959, "NBRO Recommendation N/A": null, "Proposed Measures": "Trees cLose to the houses should be removed; at least the branches should be cut down. Permission should be obtained from the Department of Forest Conservation.", "photopath": "https://raw.githubusercontent.com/MWS003-GIS/MWS003-GIS.github.io/main/IWWRMP/Data/EXD/200_photo/MWS_160/IMG_20260113_131016 Sirisamangama  (High wind).jpg" }, "geometry": { "type": "Point", "coordinates": [ 80.828959, 6.857913 ] } }
]
}
