{
"type": "FeatureCollection",
"name": "MT",
"crs": { "type": "name", "properties": { "name": "urn:ogc:def:crs:OGC:1.3:CRS84" } },
"features": [
{ "type": "Feature", "properties": { "No_": 1, "Name_of_Ta": "Kiri Uthurana Wewa", "Custodians": "DAD", "N": 6.871567, "E": 80.912888, "Remarks": "Desilting of the tank", "photopath": "https://raw.githubusercontent.com/MWS003-GIS/MWS003-GIS.github.io/main/IWWRMP/Data/EXD/200_photo/MWS_056/Kiri Uthurana Wewa.jpg" }, "geometry": { "type": "Point", "coordinates": [ 80.912888, 6.871567 ] } },
{ "type": "Feature", "properties": { "No_": 2, "Name_of_Ta": "Wewedowa Wewa", "Custodians": "DAD", "N": 6.874358, "E": 80.906028, "Remarks": "Desilting of the tank", "photopath": "https://raw.githubusercontent.com/MWS003-GIS/MWS003-GIS.github.io/main/IWWRMP/Data/EXD/200_photo/MWS_056/Wewedowa Wewa.jpg" }, "geometry": { "type": "Point", "coordinates": [ 80.906028, 6.874358 ] } },
{ "type": "Feature", "properties": { "No_": 3, "Name_of_Ta": "Kadurudeka wewa", "Custodians": "PID", "N": 6.862321, "E": 80.904038, "Remarks": "Desilting of the tank. Repairs to sluice door and provide a handrail and planting trees.", "photopath": "https://raw.githubusercontent.com/MWS003-GIS/MWS003-GIS.github.io/main/IWWRMP/Data/EXD/200_photo/MWS_056/Kadurudeka wewa.jpg" }, "geometry": { "type": "Point", "coordinates": [ 80.904038, 6.862321 ] } },
{ "type": "Feature", "properties": { "No_": 4, "Name_of_Ta": "Puna Wewa", "Custodians": "PID", "N": 6.852372, "E": 80.912003, "Remarks": "Desilting of the tank and planting trees on the reservation.", "photopath": "https://raw.githubusercontent.com/MWS003-GIS/MWS003-GIS.github.io/main/IWWRMP/Data/EXD/200_photo/MWS_056/Punawela wewa.jpg" }, "geometry": { "type": "Point", "coordinates": [ 80.912003, 6.852372 ] } }
]
}
