{
"type": "FeatureCollection",
"name": "Table 6-15",
"crs": { "type": "name", "properties": { "name": "urn:ogc:def:crs:OGC:1.3:CRS84" } },
"features": [
{ "type": "Feature", "properties": { "GND No.": "51FG", "Scheme": "Rookwood Oya", "Problem to be addressed / Recommendation": "Soil erosion of land on both sides(3km). Recommendation.\n1. Construct (3mx2mx1m) seven SABO- boulder dams across the stream where canal is steep. (Rs 630,000)\n2. Make dense planting of mixed vegetation comprising Agave/Areca nut trees /Kithul/Kumbuk/Mee/ Godapara/Kaduru/Aththikka/Wal del/Kekuna randomly mixed seedlings at 500 mm grid interval.3. Apply mulching, organic manure and NPK fertilizer. (Rs 4,005,000)\n5. Introduce grafted and VP fruit varieties of about 300 seedlings. (Rs 90,000)\nTotal Covered area 7500 m2.", "N": 7.08458, "E": 80.76112, "Estimated Cost (LKR)": "4,725,000" }, "geometry": { "type": "Point", "coordinates": [ 80.76112, 7.08458 ] } }
]
}
