{
"type": "FeatureCollection",
"name": "Table 6-17",
"crs": { "type": "name", "properties": { "name": "urn:ogc:def:crs:OGC:1.3:CRS84" } },
"features": [
{ "type": "Feature", "properties": { "No.": "2", "GN Division No.": "486B", "GN Division": "Ambewela2", "Non-point sources of pollution": "Improper disposal of household waste - Ambewela", "N or X": 7.234652, "E or Y": 80.778207, "Point sources of pollution": null, "N or X_1": null, "E or Y_1": null, "Recommended water quality improvement measures": "Preparing a separate place in home gardens for disposing household waste\nAwareness programme on how to disposal household waste properly and converting them to usable products such as compost\nFacilitating garbage collection", "Unit Cost (Rs.)": null, "Total Cost (Rs.)": "50,000.00", "Contributions (Local Community, LA, Project)": "Local/Central governments ", "Time frame for the implementation": "0.5 Years" }, "geometry": { "type": "Point", "coordinates": [ 80.778207, 7.234652 ] } },
{ "type": "Feature", "properties": { "No.": "3", "GN Division No.": "487", "GN Division": "Ganga Udagama", "Non-point sources of pollution": "Improper disposal of household waste - Ambewela", "N or X": 7.189879, "E or Y": 80.782359, "Point sources of pollution": null, "N or X_1": null, "E or Y_1": null, "Recommended water quality improvement measures": "Preparing a separate place in home gardens for disposing household waste\nAwareness programme on how to disposal household waste properly and converting them to usable products such as compost\nFacilitating garbage collection", "Unit Cost (Rs.)": null, "Total Cost (Rs.)": "50,000.00", "Contributions (Local Community, LA, Project)": "Local/Central governments ", "Time frame for the implementation": "0.5 Years" }, "geometry": { "type": "Point", "coordinates": [ 80.782359, 7.189879 ] } },
{ "type": "Feature", "properties": { "No.": "Grand Total", "GN Division No.": null, "GN Division": null, "Non-point sources of pollution": null, "N or X": null, "E or Y": null, "Point sources of pollution": null, "N or X_1": null, "E or Y_1": null, "Recommended water quality improvement measures": null, "Unit Cost (Rs.)": null, "Total Cost (Rs.)": "100000", "Contributions (Local Community, LA, Project)": null, "Time frame for the implementation": null }, "geometry": null }
]
}
