{
"type": "FeatureCollection",
"name": "DWS",
"crs": { "type": "name", "properties": { "name": "urn:ogc:def:crs:OGC:1.3:CRS84" } },
"features": [
{ "type": "Feature", "properties": { "No": 1, "GND No.": 1099, "Scheme": "Near to School", "N": 7.009934, "E": 80.539331, "Observation": "There is a 2.4m x 2.4m x 1.5m(LxWx h) water tank. It was built 40 years ago. It is in a dilapidated condition.Water is taken for drinking .There is no water filtration system. About 40 families get water from this.", "Description": "Construction of Anicut\n\nConstruction of 0.9 m high Weir across stream excluding abutments and stop planks\n\nConstruction of 1.0m high 1:3:6 (40mm) cement concrete Retaining Wall\n\n75mm tk. Stop planks (Kumbuk ) with 10mm dia. 2nos. M. S. Iron hooks and app", "Amount (Rs.)": 621500, "photopath": "https://raw.githubusercontent.com/MWS003-GIS/MWS003-GIS.github.io/main/IWWRMP/Data/EXD/200_photo/MWS_137/The water tank near the school.jpg" }, "geometry": { "type": "Point", "coordinates": [ 80.539331, 7.009934 ] } }
]
}
