{
"type": "FeatureCollection",
"name": "DWS",
"crs": { "type": "name", "properties": { "name": "urn:ogc:def:crs:OGC:1.3:CRS84" } },
"features": [
{ "type": "Feature", "properties": { "No": 2, "GND No.": "468H", "Scheme": "Halpola", "N": 7.021499, "E": 80.64802, "Observation": "There is 20000Lts storage tank has been  built there before 20 years ago .But that tank is in delapidated condition now.", "Description": "Improvements to Pini Bindu Proposed Water Project\n\nConstruction of Concrete water storage tank of 20 cum - size internal t 3mx3mx2.5\n\nIntroducing a filtering system\n\nExcavation in trenches lessthan 300mm width in normal earth average depth of not exceedi", "Amount (Rs.)": 3212000, "photopath": "https://raw.githubusercontent.com/MWS003-GIS/MWS003-GIS.github.io/main/IWWRMP/Data/EXD/200_photo/MWS_170/Halpola Temple's Well.jpg" }, "geometry": { "type": "Point", "coordinates": [ 80.64802, 7.021499 ] } }
]
}
