{
"type": "FeatureCollection",
"name": "HY_Hydro_Pt_MWS_087",
"crs": { "type": "name", "properties": { "name": "urn:ogc:def:crs:OGC:1.3:CRS84" } },
"features": [
{ "type": "Feature", "properties": { "HP_Tp_Hydr": 2, "HP_Nm_Hydr": null, "HP_Lb_meth": "8", "HP_GFCODE": "CLVTP" }, "geometry": { "type": "Point", "coordinates": [ 80.825229402561831, 7.328661315589032, 0.0 ] } },
{ "type": "Feature", "properties": { "HP_Tp_Hydr": 2, "HP_Nm_Hydr": null, "HP_Lb_meth": "8", "HP_GFCODE": "CLVTP" }, "geometry": { "type": "Point", "coordinates": [ 80.826176943104031, 7.330002140508214, 0.0 ] } },
{ "type": "Feature", "properties": { "HP_Tp_Hydr": 2, "HP_Nm_Hydr": null, "HP_Lb_meth": "8", "HP_GFCODE": "CLVTP" }, "geometry": { "type": "Point", "coordinates": [ 80.829872383664878, 7.326148528111028, 0.0 ] } },
{ "type": "Feature", "properties": { "HP_Tp_Hydr": 2, "HP_Nm_Hydr": null, "HP_Lb_meth": "8", "HP_GFCODE": "CLVTP" }, "geometry": { "type": "Point", "coordinates": [ 80.834693930234351, 7.32447952274707, 0.0 ] } },
{ "type": "Feature", "properties": { "HP_Tp_Hydr": 2, "HP_Nm_Hydr": null, "HP_Lb_meth": "8", "HP_GFCODE": "CLVTP" }, "geometry": { "type": "Point", "coordinates": [ 80.835513940739631, 7.324631490713814, 0.0 ] } },
{ "type": "Feature", "properties": { "HP_Tp_Hydr": 2, "HP_Nm_Hydr": null, "HP_Lb_meth": "8", "HP_GFCODE": "CLVTP" }, "geometry": { "type": "Point", "coordinates": [ 80.836032442362324, 7.32430869069874, 0.0 ] } },
{ "type": "Feature", "properties": { "HP_Tp_Hydr": 2, "HP_Nm_Hydr": null, "HP_Lb_meth": "8", "HP_GFCODE": "CLVTP" }, "geometry": { "type": "Point", "coordinates": [ 80.83796567078457, 7.324328693026801, 0.0 ] } },
{ "type": "Feature", "properties": { "HP_Tp_Hydr": 2, "HP_Nm_Hydr": null, "HP_Lb_meth": "8", "HP_GFCODE": "CLVTP" }, "geometry": { "type": "Point", "coordinates": [ 80.840234902540047, 7.324957575062403, 0.0 ] } },
{ "type": "Feature", "properties": { "HP_Tp_Hydr": 2, "HP_Nm_Hydr": null, "HP_Lb_meth": "8", "HP_GFCODE": "CLVTP" }, "geometry": { "type": "Point", "coordinates": [ 80.841209161782217, 7.323965448880483, 0.0 ] } }
]
}
