{
"type": "FeatureCollection",
"name": "HY_Hydro_Pt_MWS_064",
"crs": { "type": "name", "properties": { "name": "urn:ogc:def:crs:OGC:1.3:CRS84" } },
"features": [
{ "type": "Feature", "properties": { "HP_Tp_Hydr": 2, "HP_Nm_Hydr": null, "HP_Lb_meth": "8", "HP_GFCODE": "CLVTP" }, "geometry": { "type": "Point", "coordinates": [ 80.930606378513019, 6.773352947104468, 0.0 ] } },
{ "type": "Feature", "properties": { "HP_Tp_Hydr": 2, "HP_Nm_Hydr": null, "HP_Lb_meth": "8", "HP_GFCODE": "CLVTP" }, "geometry": { "type": "Point", "coordinates": [ 80.941039042897231, 6.772615902140207, 0.0 ] } },
{ "type": "Feature", "properties": { "HP_Tp_Hydr": 2, "HP_Nm_Hydr": null, "HP_Lb_meth": "8", "HP_GFCODE": "CLVTP" }, "geometry": { "type": "Point", "coordinates": [ 80.944839116404381, 6.770228677502506, 0.0 ] } },
{ "type": "Feature", "properties": { "HP_Tp_Hydr": 2, "HP_Nm_Hydr": null, "HP_Lb_meth": "8", "HP_GFCODE": "CLVTP" }, "geometry": { "type": "Point", "coordinates": [ 80.948637690194829, 6.769439246952154, 0.0 ] } },
{ "type": "Feature", "properties": { "HP_Tp_Hydr": 2, "HP_Nm_Hydr": null, "HP_Lb_meth": "8", "HP_GFCODE": "CLVTP" }, "geometry": { "type": "Point", "coordinates": [ 80.948239342049249, 6.768639706801978, 0.0 ] } },
{ "type": "Feature", "properties": { "HP_Tp_Hydr": 2, "HP_Nm_Hydr": null, "HP_Lb_meth": "8", "HP_GFCODE": "CLVTP" }, "geometry": { "type": "Point", "coordinates": [ 80.947506402088607, 6.769039127931483, 0.0 ] } },
{ "type": "Feature", "properties": { "HP_Tp_Hydr": 2, "HP_Nm_Hydr": null, "HP_Lb_meth": "8", "HP_GFCODE": "CLVTP" }, "geometry": { "type": "Point", "coordinates": [ 80.947029611315344, 6.769547108048919, 0.0 ] } },
{ "type": "Feature", "properties": { "HP_Tp_Hydr": 2, "HP_Nm_Hydr": null, "HP_Lb_meth": "8", "HP_GFCODE": "CLVTP" }, "geometry": { "type": "Point", "coordinates": [ 80.951186264922796, 6.769595780464706, 0.0 ] } },
{ "type": "Feature", "properties": { "HP_Tp_Hydr": 2, "HP_Nm_Hydr": null, "HP_Lb_meth": "8", "HP_GFCODE": "CLVTP" }, "geometry": { "type": "Point", "coordinates": [ 80.950944494994545, 6.769626039864314, 0.0 ] } },
{ "type": "Feature", "properties": { "HP_Tp_Hydr": 2, "HP_Nm_Hydr": null, "HP_Lb_meth": "8", "HP_GFCODE": "CLVTP" }, "geometry": { "type": "Point", "coordinates": [ 80.953335249792318, 6.772702830698869, 0.0 ] } },
{ "type": "Feature", "properties": { "HP_Tp_Hydr": 2, "HP_Nm_Hydr": null, "HP_Lb_meth": "8", "HP_GFCODE": "CLVTP" }, "geometry": { "type": "Point", "coordinates": [ 80.952228607285889, 6.772020604656722, 0.0 ] } },
{ "type": "Feature", "properties": { "HP_Tp_Hydr": 2, "HP_Nm_Hydr": null, "HP_Lb_meth": "8", "HP_GFCODE": "CLVTP" }, "geometry": { "type": "Point", "coordinates": [ 80.952512759467666, 6.771731642692232, 0.0 ] } },
{ "type": "Feature", "properties": { "HP_Tp_Hydr": 2, "HP_Nm_Hydr": null, "HP_Lb_meth": "8", "HP_GFCODE": "CLVTP" }, "geometry": { "type": "Point", "coordinates": [ 80.962543438492915, 6.773497522949897, 0.0 ] } },
{ "type": "Feature", "properties": { "HP_Tp_Hydr": 2, "HP_Nm_Hydr": null, "HP_Lb_meth": "8", "HP_GFCODE": "CLVTP" }, "geometry": { "type": "Point", "coordinates": [ 80.962243600369263, 6.773503356462236, 0.0 ] } },
{ "type": "Feature", "properties": { "HP_Tp_Hydr": 2, "HP_Nm_Hydr": null, "HP_Lb_meth": "8", "HP_GFCODE": "CLVTP" }, "geometry": { "type": "Point", "coordinates": [ 80.961265591058918, 6.770279238599504, 0.0 ] } },
{ "type": "Feature", "properties": { "HP_Tp_Hydr": 2, "HP_Nm_Hydr": null, "HP_Lb_meth": "8", "HP_GFCODE": "CLVTP" }, "geometry": { "type": "Point", "coordinates": [ 80.950032036957325, 6.767955710438252, 0.0 ] } },
{ "type": "Feature", "properties": { "HP_Tp_Hydr": 2, "HP_Nm_Hydr": null, "HP_Lb_meth": "9", "HP_GFCODE": "CLVTP" }, "geometry": { "type": "Point", "coordinates": [ 80.962093386511015, 6.772132305035179, 0.0 ] } }
]
}
