{
"type": "FeatureCollection",
"name": "HY_Hydro_Pt_MWS_063",
"crs": { "type": "name", "properties": { "name": "urn:ogc:def:crs:OGC:1.3:CRS84" } },
"features": [
{ "type": "Feature", "properties": { "HP_Tp_Hydr": 2, "HP_Nm_Hydr": null, "HP_Lb_meth": "8", "HP_GFCODE": "CLVTP" }, "geometry": { "type": "Point", "coordinates": [ 80.928536175288528, 6.77393354584271, 0.0 ] } }
]
}
