{
"type": "FeatureCollection",
"name": "HY_Hydro_Pt_MWS_065_1",
"crs": { "type": "name", "properties": { "name": "urn:ogc:def:crs:OGC:1.3:CRS84" } },
"features": [
{ "type": "Feature", "properties": { "HP_Tp_Hydr": 2, "HP_Nm_Hydr": null, "HP_Lb_meth": "8", "HP_GFCODE": "CLVTP" }, "geometry": { "type": "Point", "coordinates": [ 80.956739858920187, 6.869022478926497, 0.0 ] } },
{ "type": "Feature", "properties": { "HP_Tp_Hydr": 2, "HP_Nm_Hydr": null, "HP_Lb_meth": "8", "HP_GFCODE": "CLVTP" }, "geometry": { "type": "Point", "coordinates": [ 80.957583157805217, 6.869608662735989, 0.0 ] } },
{ "type": "Feature", "properties": { "HP_Tp_Hydr": 2, "HP_Nm_Hydr": null, "HP_Lb_meth": "8", "HP_GFCODE": "CLVTP" }, "geometry": { "type": "Point", "coordinates": [ 80.956762362023923, 6.869793183564917, 0.0 ] } },
{ "type": "Feature", "properties": { "HP_Tp_Hydr": 2, "HP_Nm_Hydr": null, "HP_Lb_meth": "8", "HP_GFCODE": "CLVTP" }, "geometry": { "type": "Point", "coordinates": [ 80.956251299729573, 6.873554890801199, 0.0 ] } }
]
}
