{
"type": "FeatureCollection",
"name": "HY_Hydro_Pt_MWS_103_1",
"crs": { "type": "name", "properties": { "name": "urn:ogc:def:crs:OGC:1.3:CRS84" } },
"features": [
{ "type": "Feature", "properties": { "HP_Tp_Hydr": 1, "HP_Nm_Hydr": "Paldeniya Anicut", "HP_Lb_meth": "13", "HP_GFCODE": "ANCTP" }, "geometry": { "type": "Point", "coordinates": [ 80.700282467684815, 7.324348708106261, 0.0 ] } },
{ "type": "Feature", "properties": { "HP_Tp_Hydr": 1, "HP_Nm_Hydr": "Gallida  Anicut", "HP_Lb_meth": "13", "HP_GFCODE": "ANCTP" }, "geometry": { "type": "Point", "coordinates": [ 80.7011680464054, 7.328247193282274, 0.0 ] } },
{ "type": "Feature", "properties": { "HP_Tp_Hydr": 2, "HP_Nm_Hydr": null, "HP_Lb_meth": "9", "HP_GFCODE": "CLVTP" }, "geometry": { "type": "Point", "coordinates": [ 80.696009810162721, 7.31850089417095, 0.0 ] } },
{ "type": "Feature", "properties": { "HP_Tp_Hydr": 2, "HP_Nm_Hydr": null, "HP_Lb_meth": "4", "HP_GFCODE": "TBWLP" }, "geometry": { "type": "Point", "coordinates": [ 80.704065050944948, 7.325249677114372, 0.0 ] } },
{ "type": "Feature", "properties": { "HP_Tp_Hydr": 2, "HP_Nm_Hydr": null, "HP_Lb_meth": "4", "HP_GFCODE": "TBWLP" }, "geometry": { "type": "Point", "coordinates": [ 80.701634025358771, 7.326997932077213, 0.0 ] } },
{ "type": "Feature", "properties": { "HP_Tp_Hydr": 2, "HP_Nm_Hydr": null, "HP_Lb_meth": "4", "HP_GFCODE": "CLVTP" }, "geometry": { "type": "Point", "coordinates": [ 80.718172236961806, 7.327253036983568, 0.0 ] } },
{ "type": "Feature", "properties": { "HP_Tp_Hydr": 2, "HP_Nm_Hydr": null, "HP_Lb_meth": "4", "HP_GFCODE": "CLVTP" }, "geometry": { "type": "Point", "coordinates": [ 80.71126472550894, 7.333727628412341, 0.0 ] } },
{ "type": "Feature", "properties": { "HP_Tp_Hydr": 2, "HP_Nm_Hydr": null, "HP_Lb_meth": "4", "HP_GFCODE": "CLVTP" }, "geometry": { "type": "Point", "coordinates": [ 80.715539465553107, 7.334258510605125, 0.0 ] } },
{ "type": "Feature", "properties": { "HP_Tp_Hydr": 2, "HP_Nm_Hydr": null, "HP_Lb_meth": "9", "HP_GFCODE": "CLVTP" }, "geometry": { "type": "Point", "coordinates": [ 80.708407671364739, 7.336873006000951, 0.0 ] } },
{ "type": "Feature", "properties": { "HP_Tp_Hydr": 2, "HP_Nm_Hydr": null, "HP_Lb_meth": "9", "HP_GFCODE": "CLVTP" }, "geometry": { "type": "Point", "coordinates": [ 80.710201380170403, 7.33424862331414, 0.0 ] } },
{ "type": "Feature", "properties": { "HP_Tp_Hydr": 2, "HP_Nm_Hydr": null, "HP_Lb_meth": "9", "HP_GFCODE": "CLVTP" }, "geometry": { "type": "Point", "coordinates": [ 80.714297160606364, 7.331401736138006, 0.0 ] } },
{ "type": "Feature", "properties": { "HP_Tp_Hydr": 2, "HP_Nm_Hydr": null, "HP_Lb_meth": "9", "HP_GFCODE": "CLVTP" }, "geometry": { "type": "Point", "coordinates": [ 80.703424201070618, 7.332722648117714, 0.0 ] } },
{ "type": "Feature", "properties": { "HP_Tp_Hydr": 2, "HP_Nm_Hydr": null, "HP_Lb_meth": "9", "HP_GFCODE": "CLVTP" }, "geometry": { "type": "Point", "coordinates": [ 80.714906501339613, 7.331096346024187, 0.0 ] } },
{ "type": "Feature", "properties": { "HP_Tp_Hydr": 2, "HP_Nm_Hydr": null, "HP_Lb_meth": "9", "HP_GFCODE": "CLVTP" }, "geometry": { "type": "Point", "coordinates": [ 80.714944463733204, 7.331019847116711, 0.0 ] } },
{ "type": "Feature", "properties": { "HP_Tp_Hydr": 2, "HP_Nm_Hydr": null, "HP_Lb_meth": "9", "HP_GFCODE": "CLVTP" }, "geometry": { "type": "Point", "coordinates": [ 80.702112599994166, 7.288022489813735, 0.0 ] } }
]
}
