{
"type": "FeatureCollection",
"name": "HY_Hydro_Pt_MWS_100_1",
"crs": { "type": "name", "properties": { "name": "urn:ogc:def:crs:OGC:1.3:CRS84" } },
"features": [
{ "type": "Feature", "properties": { "HP_Tp_Hydr": 2, "HP_Nm_Hydr": null, "HP_Lb_meth": "9", "HP_GFCODE": "CLVTP" }, "geometry": { "type": "Point", "coordinates": [ 80.706139291785632, 7.343468396958504, 0.0 ] } },
{ "type": "Feature", "properties": { "HP_Tp_Hydr": 2, "HP_Nm_Hydr": null, "HP_Lb_meth": "9", "HP_GFCODE": "CLVTP" }, "geometry": { "type": "Point", "coordinates": [ 80.713315162699999, 7.342844925516919, 0.0 ] } },
{ "type": "Feature", "properties": { "HP_Tp_Hydr": 2, "HP_Nm_Hydr": null, "HP_Lb_meth": "4", "HP_GFCODE": "TBWLP" }, "geometry": { "type": "Point", "coordinates": [ 80.709885556205734, 7.349405602365729, 0.0 ] } },
{ "type": "Feature", "properties": { "HP_Tp_Hydr": 2, "HP_Nm_Hydr": null, "HP_Lb_meth": "4", "HP_GFCODE": "TBWLP" }, "geometry": { "type": "Point", "coordinates": [ 80.708027904807864, 7.345643694471467, 0.0 ] } },
{ "type": "Feature", "properties": { "HP_Tp_Hydr": 2, "HP_Nm_Hydr": null, "HP_Lb_meth": "4", "HP_GFCODE": "TBWLP" }, "geometry": { "type": "Point", "coordinates": [ 80.701482913600287, 7.34616768881476, 0.0 ] } },
{ "type": "Feature", "properties": { "HP_Tp_Hydr": 2, "HP_Nm_Hydr": null, "HP_Lb_meth": "4", "HP_GFCODE": "CLVTP" }, "geometry": { "type": "Point", "coordinates": [ 80.703060226285643, 7.351243258081237, 0.0 ] } },
{ "type": "Feature", "properties": { "HP_Tp_Hydr": 2, "HP_Nm_Hydr": null, "HP_Lb_meth": "4", "HP_GFCODE": "CLVTP" }, "geometry": { "type": "Point", "coordinates": [ 80.704186696498311, 7.348272082701198, 0.0 ] } }
]
}
