{
"type": "FeatureCollection",
"name": "HY_Hydro_Pt_MWS_115_1",
"crs": { "type": "name", "properties": { "name": "urn:ogc:def:crs:OGC:1.3:CRS84" } },
"features": [
{ "type": "Feature", "properties": { "HP_Tp_Hydr": 2, "HP_Nm_Hydr": null, "HP_Lb_meth": "9", "HP_GFCODE": "CLVTP" }, "geometry": { "type": "Point", "coordinates": [ 80.547524623371714, 7.363747825435969, 0.0 ] } },
{ "type": "Feature", "properties": { "HP_Tp_Hydr": 2, "HP_Nm_Hydr": null, "HP_Lb_meth": "9", "HP_GFCODE": "CLVTP" }, "geometry": { "type": "Point", "coordinates": [ 80.550317580855406, 7.363435000026571, 0.0 ] } },
{ "type": "Feature", "properties": { "HP_Tp_Hydr": 2, "HP_Nm_Hydr": null, "HP_Lb_meth": "9", "HP_GFCODE": "CLVTP" }, "geometry": { "type": "Point", "coordinates": [ 80.555024806327211, 7.36528391362213, 0.0 ] } },
{ "type": "Feature", "properties": { "HP_Tp_Hydr": 1, "HP_Nm_Hydr": "Bulathpela Amuna", "HP_Lb_meth": "13", "HP_GFCODE": "ANCTP" }, "geometry": { "type": "Point", "coordinates": [ 80.55423578044028, 7.346764915476929, 0.0 ] } },
{ "type": "Feature", "properties": { "HP_Tp_Hydr": 2, "HP_Nm_Hydr": null, "HP_Lb_meth": "4", "HP_GFCODE": "WELLP" }, "geometry": { "type": "Point", "coordinates": [ 80.56008180878365, 7.344517888314901, 0.0 ] } },
{ "type": "Feature", "properties": { "HP_Tp_Hydr": 2, "HP_Nm_Hydr": null, "HP_Lb_meth": "9", "HP_GFCODE": "CLVTP" }, "geometry": { "type": "Point", "coordinates": [ 80.556674734962527, 7.344729792076728, 0.0 ] } }
]
}
