{
"type": "FeatureCollection",
"name": "DWS",
"crs": { "type": "name", "properties": { "name": "urn:ogc:def:crs:OGC:1.3:CRS84" } },
"features": [
{ "type": "Feature", "properties": { "No": 13, "GND No.": "475H", "Scheme": "Thalankanda Estate", "N": 6.898143, "E": 80.676277, "Observation": "need to remake the existing tank or remake a new stock tank (10000 L) and water pipeline 2 inches for 2km", "Description": "Construction of Concrete water storage tank of 20 cum - size internal t 3mx3mx2.5\n\nExcavation in trenches less than 300mm width in normal earth average depth of not exceeding 1.0m from ground level inclusive of back filling, compacting and disposal of su", "Estimated Cost": 4823500, "photopath": "https://raw.githubusercontent.com/MWS003-GIS/MWS003-GIS.github.io/main/IWWRMP/Data/EXD/200_photo/MWS_152/Thanakanda water tank.jpg" }, "geometry": { "type": "Point", "coordinates": [ 80.676277, 6.898143 ] } },
{ "type": "Feature", "properties": { "No": 14, "GND No.": "475H", "Scheme": "Trilkultri Estate", "N": 6.90103, "E": 80.683564, "Observation": "need to remake the stock tank of 5000 l tank", "Description": "Construction of Concrete water storage tank of 20 cum - size internal t 3mx3mx2.5\n\nMiscellaneous\n\nContingencies 10%", "Estimated Cost": 759000, "photopath": "https://raw.githubusercontent.com/MWS003-GIS/MWS003-GIS.github.io/main/IWWRMP/Data/EXD/200_photo/MWS_152/Trilikutti (2).jpg" }, "geometry": { "type": "Point", "coordinates": [ 80.683564, 6.90103 ] } },
{ "type": "Feature", "properties": { "No": 15, "GND No.": "475H", "Scheme": "No 9  Faciban Estate", "N": 6.894255, "E": 80.698744, "Observation": "need to replace the existing valve (25 mm,1 inch section valve),clean the recourse area, need 500m iron tube.", "Description": "Supplying of Brass Gate Valve 1\" - S lon (Vito)\n\nSupplying of 2.0mm thick,1\" thread size (33.5mm avg.outside dia.)GI Pipe\n\nClearing the area\n\nMiscellaneous\n\nContingencies 10%", "Estimated Cost": 286000, "photopath": "https://raw.githubusercontent.com/MWS003-GIS/MWS003-GIS.github.io/main/IWWRMP/Data/EXD/200_photo/MWS_152/No9 Frasifan.jpg" }, "geometry": { "type": "Point", "coordinates": [ 80.698744, 6.894255 ] } },
{ "type": "Feature", "properties": { "No": 16, "GND No.": "475H", "Scheme": "No8 well Frasifan", "N": 6.916853, "E": 80.675691, "Observation": "need 1 km pipe line of 2 inches", "Description": "Excavation in trenches less than 300mm width in normal earth average depth of not exceeding 1.0m from ground level inclusive of back filling, compacting and disposal of surplus earth (Excavation  by Machine)\n\nSupplying & laying 50mm Dia PVC pipe line in", "Estimated Cost": 2057000, "photopath": "https://raw.githubusercontent.com/MWS003-GIS/MWS003-GIS.github.io/main/IWWRMP/Data/EXD/200_photo/MWS_152/No8 well Frasifan.jpg" }, "geometry": { "type": "Point", "coordinates": [ 80.675691, 6.916853 ] } }
]
}
