{
"type": "FeatureCollection",
"name": "Landslides",
"crs": { "type": "name", "properties": { "name": "urn:ogc:def:crs:OGC:1.3:CRS84" } },
"features": [
{ "type": "Feature", "properties": { "No_": 2, "MWS_ID": 88, "GN_Divisio": 804, "GN_Divis_1": "Hatheyalwela", "Land_Slide": "1. Landlide - Pachchakadu area", "N": 7.316263, "E": 80.831108, "NBRO_Recom": "Needs NBRO concern", "Proposed_M": "Construction of stone terraces and live fence is suitable for the soil conservation. Necessary stone are availableion the land.", "photopath": "https://raw.githubusercontent.com/MWS003-GIS/MWS003-GIS.github.io/main/IWWRMP/Data/EXD/200_photo/MWS_088/Landslide pachchakadu area.jpg" }, "geometry": { "type": "Point", "coordinates": [ 80.831108, 7.316263 ] } },
{ "type": "Feature", "properties": { "No_": 3, "MWS_ID": 88, "GN_Divisio": 804, "GN_Divis_1": "Hatheyalwela", "Land_Slide": "2. Road erosion - Private Estate", "N": 7.307218, "E": 80.824623, "NBRO_Recom": "Needs NBRO concern", "Proposed_M": "Construction of stone terraces and live fence is suitable for the soil conservation. Necessary stone are availableion the land.", "photopath": "https://raw.githubusercontent.com/MWS003-GIS/MWS003-GIS.github.io/main/IWWRMP/Data/EXD/200_photo/MWS_088/Landslide Pudgakikawaththa area.jpg" }, "geometry": { "type": "Point", "coordinates": [ 80.824623, 7.307218 ] } },
{ "type": "Feature", "properties": { "No_": 5, "MWS_ID": 88, "GN_Divisio": 806, "GN_Divis_1": "Mangoda", "Land_Slide": "1. Landlide - Gale kele, Mr. Premathilaka home", "N": 7.289971, "E": 80.833379, "NBRO_Recom": "NBRO is aware", "Proposed_M": "Suitable allotments of lands should be given in another area. Follow NBRO instructions.", "photopath": "https://raw.githubusercontent.com/MWS003-GIS/MWS003-GIS.github.io/main/IWWRMP/Data/EXD/200_photo/MWS_088/Landslide -Premathilaka home.jpg" }, "geometry": { "type": "Point", "coordinates": [ 80.833379, 7.289971 ] } },
{ "type": "Feature", "properties": { "No_": 6, "MWS_ID": 88, "GN_Divisio": 806, "GN_Divis_1": "Mangoda", "Land_Slide": "2. Landlide - Bombrawa 172/16B and 172/19 home", "N": 7.291774, "E": 80.836387, "NBRO_Recom": "Needs NBRO concern", "Proposed_M": "Suitable allotments of lands should be given in another area. Follow NBRO instructions.", "photopath": "https://raw.githubusercontent.com/MWS003-GIS/MWS003-GIS.github.io/main/IWWRMP/Data/EXD/200_photo/MWS_088/Landslide 172-16 B  home.jpg" }, "geometry": { "type": "Point", "coordinates": [ 80.836387, 7.291774 ] } },
{ "type": "Feature", "properties": { "No_": 7, "MWS_ID": 88, "GN_Divisio": 807, "GN_Divis_1": "Rambukpotha", "Land_Slide": "1. Landslide - Galekele", "N": 7.29501, "E": 80.848643, "NBRO_Recom": "Needs NBRO concern", "Proposed_M": "Construction of stone terraces and live fence is suitable for the soil conservation. It is appropriate to construct a 20 m long 3 m high retaining wall near the main road. Follow the recommendations of NBRO.", "photopath": "https://raw.githubusercontent.com/MWS003-GIS/MWS003-GIS.github.io/main/IWWRMP/Data/EXD/200_photo/MWS_088/Galekele land slide.jpg" }, "geometry": { "type": "Point", "coordinates": [ 80.848643, 7.29501 ] } }
]
}
