{
"type": "FeatureCollection",
"name": "MT",
"crs": { "type": "name", "properties": { "name": "urn:ogc:def:crs:OGC:1.3:CRS84" } },
"features": [
{ "type": "Feature", "properties": { "No": 1, "MWS_ID": 88, "Name_of_Ta": "Udawela Wewa", "Custodians": "DAD", "N": 7.299223, "E": 80.823485, "Remarks": "Rehabilitation of the tank and desilting.", "photopath": "https://raw.githubusercontent.com/MWS003-GIS/MWS003-GIS.github.io/main/IWWRMP/Data/EXD/200_photo/MWS_088/Udawela lake.jpg" }, "geometry": { "type": "Point", "coordinates": [ 80.823485, 7.299223 ] } }
]
}
