{
"type": "FeatureCollection",
"name": "WP",
"crs": { "type": "name", "properties": { "name": "urn:ogc:def:crs:OGC:1.3:CRS84" } },
"features": [
{ "type": "Feature", "properties": { "No_": 2, "MWS_ID": 88, "GN_Divisio": 804, "GN_Divis_1": "Hatheyalwela", "Non_point": "Potential to add human waste - Withalawa Estate", "N": 7.3128397, "E": 80.8326191, "No__of_Toi": "96", "Point_sour": "-", "N_1": "-", "E_1": "-", "Recommende": "-", "Unit_Cost": "-", "Total_Cost": "-", "Contributi": "-", "Time_frame": "-", "photopath": "https://raw.githubusercontent.com/MWS003-GIS/MWS003-GIS.github.io/main/IWWRMP/Data/EXD/200_photo/MWS_088/Garbage Disposal (2).jpg" }, "geometry": { "type": "Point", "coordinates": [ 80.8326191, 7.3128397 ] } },
{ "type": "Feature", "properties": { "No_": 3, "MWS_ID": 88, "GN_Divisio": 804, "GN_Divis_1": "Hatheyalwela", "Non_point": "Informal disposal of houshold wastes/garbage", "N": 7.3128397, "E": 80.8326191, "No__of_Toi": "-", "Point_sour": "-", "N_1": "-", "E_1": "-", "Recommende": "Preparing a separate place in homegardens for disposing houshold waste,Awareness programme on how to disposal household waste properly and converting them to usable products such as compost,Facilitating garbage collection", "Unit_Cost": "-", "Total_Cost": "50,000.00", "Contributi": "Local/Central governments", "Time_frame": "0.5 Years", "photopath": "https://raw.githubusercontent.com/MWS003-GIS/MWS003-GIS.github.io/main/IWWRMP/Data/EXD/200_photo/MWS_088/Garbage disposal.jpg" }, "geometry": { "type": "Point", "coordinates": [ 80.8326191, 7.3128397 ] } }
]
}
