{
"type": "FeatureCollection",
"name": "MT",
"crs": { "type": "name", "properties": { "name": "urn:ogc:def:crs:OGC:1.3:CRS84" } },
"features": [
{ "type": "Feature", "properties": { "Name_of_Ta": "Haldola Wewa", "Custodians": "DAD", "N": 7.098941, "E": 80.525863, "Remarks": "Desilting and plant trees in the reservation and mark boundaries.", "photopath": "-" }, "geometry": { "type": "Point", "coordinates": [ 80.525863, 7.098941 ] } }
]
}
