{
"type": "FeatureCollection",
"name": "Landslides",
"crs": { "type": "name", "properties": { "name": "urn:ogc:def:crs:OGC:1.3:CRS84" } },
"features": [
{ "type": "Feature", "properties": { "No.": 1, "MWS_ID": "100-1", "GN Divisio": 646, "GN Divis_1": "Galpihilla", "Land Slide": "Landslide -  Niyadagala area (In 1956)", "N or X": 7.353791, "E or Y": 80.712616, "Add. Coord": "-", "NBRO Recom": "NBRO is aware", "Proposed M": "Allotment of lands at another area" }, "geometry": { "type": "Point", "coordinates": [ 80.712616, 7.353791 ] } },
{ "type": "Feature", "properties": { "No.": 2, "MWS_ID": "100-1", "GN Divisio": 646, "GN Divis_1": "Galpihilla", "Land Slide": "Landslide - Puwakgolla area (In 1956)", "N or X": 7.354289, "E or Y": 80.71263, "Add. Coord": "-", "NBRO Recom": "NBRO is aware", "Proposed M": "Allotment of lands at another area" }, "geometry": { "type": "Point", "coordinates": [ 80.71263, 7.354289 ] } }
]
}
