{
"type": "FeatureCollection",
"name": "Table 6-15",
"crs": { "type": "name", "properties": { "name": "urn:ogc:def:crs:OGC:1.3:CRS84" } },
"features": [
{ "type": "Feature", "properties": { "No.": 1, "GN Division No.": "501G", "GN Division": "Hope", "Non-point sources of pollution": "No special issues reported", "N or X": null, "E or Y": null, "Point sources of pollution": null, "N or X_1": null, "E or Y_1": null, "Recommended water quality improvement measures": null, "Unit Cost (Rs.)": null, "Total Cost (Rs.)": null, "Contributions (Local Community, LA, Project)": null, "Time frame for the implementation": null }, "geometry": null },
{ "type": "Feature", "properties": { "No.": 2, "GN Division No.": "499 G", "GN Division": "Kirimetiya2", "Non-point sources of pollution": "No special issues reported", "N or X": null, "E or Y": null, "Point sources of pollution": null, "N or X_1": null, "E or Y_1": null, "Recommended water quality improvement measures": null, "Unit Cost (Rs.)": null, "Total Cost (Rs.)": null, "Contributions (Local Community, LA, Project)": null, "Time frame for the implementation": null }, "geometry": null },
{ "type": "Feature", "properties": { "No.": 3, "GN Division No.": "501B", "GN Division": "Muloya", "Non-point sources of pollution": "Improper disposal of waste", "N or X": 7.093153, "E or Y": 80.750548, "Point sources of pollution": null, "N or X_1": null, "E or Y_1": null, "Recommended water quality improvement measures": "Preparing a separate place in home gardens for disposing household waste", "Unit Cost (Rs.)": null, "Total Cost (Rs.)": null, "Contributions (Local Community, LA, Project)": "Local/Central governments ", "Time frame for the implementation": "0.5 Years" }, "geometry": { "type": "Point", "coordinates": [ 80.750548, 7.093153 ] } },
{ "type": "Feature", "properties": { "No.": 4, "GN Division No.": "501B", "GN Division": "Muloya", "Non-point sources of pollution": "Addition of household wastes/garbage to water sources", "N or X": 7.091151, "E or Y": 80.749759, "Point sources of pollution": null, "N or X_1": null, "E or Y_1": null, "Recommended water quality improvement measures": "Awareness programme on how to disposal household waste properly and converting them to usable products such as compost\nFacilitating garbage collection", "Unit Cost (Rs.)": null, "Total Cost (Rs.)": "50,000.00", "Contributions (Local Community, LA, Project)": null, "Time frame for the implementation": null }, "geometry": { "type": "Point", "coordinates": [ 80.749759, 7.091151 ] } },
{ "type": "Feature", "properties": { "No.": 5, "GN Division No.": "501", "GN Division": "Rahathungoda", "Non-point sources of pollution": "No special issues reported", "N or X": null, "E or Y": null, "Point sources of pollution": null, "N or X_1": null, "E or Y_1": null, "Recommended water quality improvement measures": null, "Unit Cost (Rs.)": null, "Total Cost (Rs.)": null, "Contributions (Local Community, LA, Project)": null, "Time frame for the implementation": null }, "geometry": null },
{ "type": "Feature", "properties": { "No.": 6, "GN Division No.": "501F", "GN Division": "Rookwood Estate", "Non-point sources of pollution": "No special issues reported", "N or X": null, "E or Y": null, "Point sources of pollution": null, "N or X_1": null, "E or Y_1": null, "Recommended water quality improvement measures": null, "Unit Cost (Rs.)": null, "Total Cost (Rs.)": null, "Contributions (Local Community, LA, Project)": null, "Time frame for the implementation": null }, "geometry": null },
{ "type": "Feature", "properties": { "No.": null, "GN Division No.": null, "GN Division": null, "Non-point sources of pollution": null, "N or X": null, "E or Y": null, "Point sources of pollution": null, "N or X_1": null, "E or Y_1": null, "Recommended water quality improvement measures": null, "Unit Cost (Rs.)": null, "Total Cost (Rs.)": "50,000.00", "Contributions (Local Community, LA, Project)": null, "Time frame for the implementation": null }, "geometry": null }
]
}
