{
"type": "FeatureCollection",
"name": "Table 6_2",
"crs": { "type": "name", "properties": { "name": "urn:ogc:def:crs:OGC:1.3:CRS84" } },
"features": [
{ "type": "Feature", "properties": { "No.": 3, "GN Division No.": "501B", "GN Division": "Muloya", "Land Slides": "Soil sloughing, breaking/collapsing walls of the buildings - - Muloya Regional Hospital", "N or X": 7.09745, "E or Y": 80.750984, "NBRO Recommendation": "Needs NBRO concern", "Proposed Measures": "Establishing a rubble masonry wall (30 m x 3.6 m)", "photopath": "-" }, "geometry": { "type": "Point", "coordinates": [ 80.750984, 7.09745 ] } }
]
}
