{
"type": "FeatureCollection",
"name": "Table_6_14",
"crs": { "type": "name", "properties": { "name": "urn:ogc:def:crs:OGC:1.3:CRS84" } },
"features": [
{ "type": "Feature", "properties": { "No.": 1, "GN Division No.": 1002, "GN Division": "Udamailapitiya South", "Non-point sources of pollution": "Addition of various household waste to water ways at Undamailapitiya tank", "N or X": 7.218153, "E or Y": 80.765526, "Point sources of pollution": "-", "Add. N or X": "-", "Add. E or Y": "-", "Recommended water quality improvement measures": "Awareness programs and placing bins for collecting waste", "Unit Cost (Rs.)": "-", "Total Cost (Rs.)": "50,000", "Contributions (Local Community, LA, Project)": "Local Government", "Time frame for the implementation": "0.5 Years", "photopath": "https://raw.githubusercontent.com/MWS003-GIS/MWS003-GIS.github.io/main/IWWRMP/Data/EXD/200_photo/MWS_008_1/Udamayilapitiya_South/MS17.jpg" }, "geometry": { "type": "Point", "coordinates": [ 80.765526, 7.218153 ] } },
{ "type": "Feature", "properties": { "No.": 2, "GN Division No.": 1019, "GN Division": "Poththagoda", "Non-point sources of pollution": "Addition of various wastes including plastic, polythene etc. to water draining lines - Dehalkada Ambalama", "N or X": 7.199219, "E or Y": 80.74613, "Point sources of pollution": "-", "Add. N or X": "-", "Add. E or Y": "-", "Recommended water quality improvement measures": "Awareness programs and placing bins for collecting waste", "Unit Cost (Rs.)": "-", "Total Cost (Rs.)": "50,000", "Contributions (Local Community, LA, Project)": "Local Government", "Time frame for the implementation": "0.5 Years", "photopath": "https://raw.githubusercontent.com/MWS003-GIS/MWS003-GIS.github.io/main/IWWRMP/Data/EXD/200_photo/MWS_008_1/Pothgoda/PTG0701.jpg" }, "geometry": { "type": "Point", "coordinates": [ 80.74613, 7.199219 ] } },
{ "type": "Feature", "properties": { "No.": 3, "GN Division No.": 1020, "GN Division": "Neelawala", "Non-point sources of pollution": "Addition of various wastes including plastic, polythene etc. to Murapola Ela", "N or X": 7.187128, "E or Y": 80.740843, "Point sources of pollution": "-", "Add. N or X": "-", "Add. E or Y": "-", "Recommended water quality improvement measures": "Awareness programs and placing bins for collecting waste\nEstablishing a net to collect wastes", "Unit Cost (Rs.)": "-", "Total Cost (Rs.)": "50000\n300000", "Contributions (Local Community, LA, Project)": "Local Government", "Time frame for the implementation": "0.5 Years", "photopath": "-" }, "geometry": { "type": "Point", "coordinates": [ 80.740843, 7.187128 ] } },
{ "type": "Feature", "properties": { "No.": 4, "GN Division No.": 1024, "GN Division": "Unuvinna East", "Non-point sources of pollution": "Addition of various household waste to Pallema Oya", "N or X": 7.214173, "E or Y": 80.766849, "Point sources of pollution": "-", "Add. N or X": "-", "Add. E or Y": "-", "Recommended water quality improvement measures": "Awareness programs and placing bins for collecting waste and introduce a proper schedule for collecting waste", "Unit Cost (Rs.)": "-", "Total Cost (Rs.)": "50,000", "Contributions (Local Community, LA, Project)": "Local Government", "Time frame for the implementation": "0.5 Years", "photopath": "https://raw.githubusercontent.com/MWS003-GIS/MWS003-GIS.github.io/main/IWWRMP/Data/EXD/200_photo/MWS_008_1/Unuwinna_East/UN(08)1.jpg" }, "geometry": { "type": "Point", "coordinates": [ 80.766849, 7.214173 ] } }
]
}
