{
"type": "FeatureCollection",
"name": "Table 6-3",
"crs": { "type": "name", "properties": { "name": "urn:ogc:def:crs:OGC:1.3:CRS84" } },
"features": [
{ "type": "Feature", "properties": { "Tank name": "Millapokuna Tank", "Land ownership": "DAD", "N": 7.214485, "E": 80.759116, "Remarks": "Recommended to desilt the tank and improve reservation" }, "geometry": { "type": "Point", "coordinates": [ 80.759116, 7.214485 ] } }
]
}
