{
"type": "FeatureCollection",
"name": "MT",
"crs": { "type": "name", "properties": { "name": "urn:ogc:def:crs:OGC:1.3:CRS84" } },
"features": [
{ "type": "Feature", "properties": { "Name_of_Ta": "Templesto Janapadaya", "Custodians": null, "N": 6.948903, "E": 80.537652, "Remarks": "Mark boundaries to show the reservation. Reservation has been encroached.", "photopath": "https://raw.githubusercontent.com/MWS003-GIS/MWS003-GIS.github.io/main/IWWRMP/Data/EXD/200_photo/MWS_144_2/Pond - Templesto Janapadaya.jpg" }, "geometry": { "type": "Point", "coordinates": [ 80.537652, 6.948903 ] } }
]
}
