{
"type": "FeatureCollection",
"name": "SWC_OFF",
"crs": { "type": "name", "properties": { "name": "urn:ogc:def:crs:OGC:1.3:CRS84" } },
"features": [
{ "type": "Feature", "properties": { "No_": 3, "MWS_ID": 49, "GN_Divisio": "37B", "GN_Divis_1": "Kindigoda", "Key_Activi": "1. Establishing a retaining wall - Gemidiriya multipurpouse building", "Priority_b": "-", "N": 7.018518, "E": 80.94108, "Quantity": "14 m x 3 m", "Proposed_m": "Retaining Wall (Concrete)", "Total_Cost": "1,633,500.00", "Contributi": "By the project", "Time_frame": "0.25 Years", "photopath": "https://raw.githubusercontent.com/MWS003-GIS/MWS003-GIS.github.io/main/IWWRMP/Data/EXD/200_photo/MWS_049/IMG_20250709_103015 Kindigoda canal.jpg" }, "geometry": { "type": "Point", "coordinates": [ 80.94108, 7.018518 ] } },
{ "type": "Feature", "properties": { "No_": 7, "MWS_ID": 49, "GN_Divisio": "38", "GN_Divis_1": "Wewegama", "Key_Activi": "1. Establishing a drain", "Priority_b": "-", "N": 7.001089, "E": 80.937567, "Quantity": "100 m", "Proposed_m": "Concrete Drain", "Total_Cost": "6,017,000.00", "Contributi": "By the project", "Time_frame": "0.25 Years", "photopath": "https://raw.githubusercontent.com/MWS003-GIS/MWS003-GIS.github.io/main/IWWRMP/Data/EXD/200_photo/MWS_049/IMG_20250703_102541 Wewahena lake.jpg" }, "geometry": { "type": "Point", "coordinates": [ 80.937567, 7.001089 ] } }
]
}
