{
"type": "FeatureCollection",
"name": "MT",
"crs": { "type": "name", "properties": { "name": "urn:ogc:def:crs:OGC:1.3:CRS84" } },
"features": [
{ "type": "Feature", "properties": { "No": 1, "Name of th": "Dam Division Lake", "Custodians": "Plantation Company", "Location N": 7.076604, "Location E": 80.860188, "Remarks": "Desilting and repair sluice and spill", "photopath": "https://raw.githubusercontent.com/MWS003-GIS/MWS003-GIS.github.io/main/IWWRMP/Data/EXD/200_photo/MWS_027/12. Dam Division Lake.jpg" }, "geometry": { "type": "Point", "coordinates": [ 80.860188, 7.076604 ] } },
{ "type": "Feature", "properties": { "No": 2, "Name of th": "Katukithula wewa", "Custodians": "Plantation Company", "Location N": 7.08122, "Location E": 80.86323, "Remarks": "Desilting, and remove water weeds. Reconstruct sluice.", "photopath": "https://raw.githubusercontent.com/MWS003-GIS/MWS003-GIS.github.io/main/IWWRMP/Data/EXD/200_photo/MWS_027/14. Katukithule Wewa.jpg" }, "geometry": { "type": "Point", "coordinates": [ 80.86323, 7.08122 ] } },
{ "type": "Feature", "properties": { "No": 3, "Name of th": "Halmee wewa", "Custodians": "DAD", "Location N": 7.068322, "Location E": 80.880055, "Remarks": "Repair tanks bund and sluice. Desilt the tank", "photopath": "https://raw.githubusercontent.com/MWS003-GIS/MWS003-GIS.github.io/main/IWWRMP/Data/EXD/200_photo/MWS_027/7. Halmee Wewa.jpg" }, "geometry": { "type": "Point", "coordinates": [ 80.880055, 7.068322 ] } },
{ "type": "Feature", "properties": { "No": 4, "Name of th": "Maha Kendagaha Madiththa wewa", "Custodians": "DAD", "Location N": 7.074675, "Location E": 80.879567, "Remarks": "Replace sluice gate. Raise the bund.", "photopath": "https://raw.githubusercontent.com/MWS003-GIS/MWS003-GIS.github.io/main/IWWRMP/Data/EXD/200_photo/MWS_027/10. Maha Kenda Madiththa Wewa.jpg" }, "geometry": { "type": "Point", "coordinates": [ 80.879567, 7.074675 ] } },
{ "type": "Feature", "properties": { "No": 5, "Name of th": "Nattaramandiya", "Custodians": "-", "Location N": 7.076108, "Location E": 80.884692, "Remarks": "Construct sluice and spill. Desilt tank.", "photopath": "https://raw.githubusercontent.com/MWS003-GIS/MWS003-GIS.github.io/main/IWWRMP/Data/EXD/200_photo/MWS_027/6. Naththara Mandiya Ulpatha Wewa.jpg" }, "geometry": { "type": "Point", "coordinates": [ 80.884692, 7.076108 ] } },
{ "type": "Feature", "properties": { "No": 6, "Name of th": "Kendagaha Maditta wewa", "Custodians": "DAD", "Location N": 7.075802, "Location E": 80.879732, "Remarks": "Replace the sluice gate and desilt.", "photopath": "https://raw.githubusercontent.com/MWS003-GIS/MWS003-GIS.github.io/main/IWWRMP/Data/EXD/200_photo/MWS_027/1. Kendagaha Maditta Wewa.jpg" }, "geometry": { "type": "Point", "coordinates": [ 80.879732, 7.075802 ] } },
{ "type": "Feature", "properties": { "No": 7, "Name of th": "Pambe wewa", "Custodians": "DAD", "Location N": 7.073112, "Location E": 80.881385, "Remarks": "Desilt.", "photopath": "https://raw.githubusercontent.com/MWS003-GIS/MWS003-GIS.github.io/main/IWWRMP/Data/EXD/200_photo/MWS_027/3. Pambe Wewa.jpg" }, "geometry": { "type": "Point", "coordinates": [ 80.881385, 7.073112 ] } },
{ "type": "Feature", "properties": { "No": 8, "Name of th": "Ala Pala wewa", "Custodians": "DAD", "Location N": 7.062957, "Location E": 80.875518, "Remarks": "Not recommended for development.", "photopath": "https://raw.githubusercontent.com/MWS003-GIS/MWS003-GIS.github.io/main/IWWRMP/Data/EXD/200_photo/MWS_027/Alapala Wewa.jpg" }, "geometry": { "type": "Point", "coordinates": [ 80.875518, 7.062957 ] } }
]
}
