{
"type": "FeatureCollection",
"name": "Table_6_3",
"crs": { "type": "name", "properties": { "name": "urn:ogc:def:crs:OGC:1.3:CRS84" } },
"features": [
{ "type": "Feature", "properties": { "No": 1, "Name of th": "Dam Division Lake", "Custodians": "Plantation Company", "N": 7.076604, "E": 80.860188, "Remarks": "Desilting and repair sluice and spill" }, "geometry": { "type": "Point", "coordinates": [ 80.860188, 7.076604 ] } },
{ "type": "Feature", "properties": { "No": 2, "Name of th": "Katukithula wewa", "Custodians": "Plantation Company", "N": 7.08122, "E": 80.86323, "Remarks": "Desilting, and remove water weeds. Reconstruct sluice." }, "geometry": { "type": "Point", "coordinates": [ 80.86323, 7.08122 ] } },
{ "type": "Feature", "properties": { "No": 3, "Name of th": "Halmee wewa", "Custodians": "DAD", "N": 7.068322, "E": 80.880055, "Remarks": "Repair tanks bund and sluice. Desilt the tank" }, "geometry": { "type": "Point", "coordinates": [ 80.880055, 7.068322 ] } },
{ "type": "Feature", "properties": { "No": 4, "Name of th": "Maha Kendagaha Madiththa wewa", "Custodians": "DAD", "N": 7.074675, "E": 80.879567, "Remarks": "Replace sluice gate. Raise the bund." }, "geometry": { "type": "Point", "coordinates": [ 80.879567, 7.074675 ] } },
{ "type": "Feature", "properties": { "No": 5, "Name of th": "Nattaramandiya", "Custodians": "-", "N": 7.076108, "E": 80.884692, "Remarks": "Construct sluice and spill. Desilt tank." }, "geometry": { "type": "Point", "coordinates": [ 80.884692, 7.076108 ] } },
{ "type": "Feature", "properties": { "No": 6, "Name of th": "Kendagaha Maditta wewa", "Custodians": "DAD", "N": 7.075802, "E": 80.879732, "Remarks": "Replace the sluice gate and desilt." }, "geometry": { "type": "Point", "coordinates": [ 80.879732, 7.075802 ] } },
{ "type": "Feature", "properties": { "No": 7, "Name of th": "Pambe wewa", "Custodians": "DAD", "N": 7.073112, "E": 80.881385, "Remarks": "Desilt." }, "geometry": { "type": "Point", "coordinates": [ 80.881385, 7.073112 ] } },
{ "type": "Feature", "properties": { "No": 8, "Name of th": "Ala Pala wewa", "Custodians": "DAD", "N": 7.062957, "E": 80.875518, "Remarks": "Not recommended for development." }, "geometry": { "type": "Point", "coordinates": [ 80.875518, 7.062957 ] } }
]
}
