{
"type": "FeatureCollection",
"name": "Table_6_29",
"crs": { "type": "name", "properties": { "name": "urn:ogc:def:crs:OGC:1.3:CRS84" } },
"features": [
{ "type": "Feature", "properties": { "No": 2, "GND No.": "516", "Descriptio": "Hunuketiya Kandura", "N": 7.106619, "E": 80.877315, "Observatio": "During the rainy season when too much water flows, Bank erosion occurs", "Descript_1": "9\" thk flat Rubble paving in 1:6 Cement mortarVegetative cover improving (1.5m-2.0m wide) with Areca nut seedlings @ 1.5m spacing in two rows, Beetle creeper VP @ 3m spacing in a single row, Green gram as a cover crop including applying of compost manure", "Amount (Rs": "150,575.00" }, "geometry": { "type": "Point", "coordinates": [ 80.877315, 7.106619 ] } },
{ "type": "Feature", "properties": { "No": 3, "GND No.": "516", "Descriptio": "Keena Kandura", "N": 7.103641, "E": 80.875632, "Observatio": "During the rainy season when too much water flows, Bank erosion occurs", "Descript_1": "9\" thk flat Rubble paving in 1:6 Cement mortarVegetative cover improving (1.5m-2.0m wide) with Areca nut seedlings @ 1.5m spacing in two rows, Beetle creeper VP @ 3m spacing in a single row, Green gram as a cover crop including applying of compost manure", "Amount (Rs": "148,225.00" }, "geometry": { "type": "Point", "coordinates": [ 80.875632, 7.103641 ] } },
{ "type": "Feature", "properties": { "No": 4, "GND No.": "516B", "Descriptio": "Yakkatuwa Oya", "N": 7.082263, "E": 80.872972, "Observatio": "During the rainy season when too much water flows, Bank erosion occurs", "Descript_1": "Vegetative cover improving (1.5m-2.0m wide) with Areca nut seedlings @ 1.5m spacing in two rows, Beetle creeper VP @ 3m spacing in a single row, Green gram as a cover crop including applying of compost manure, NPK fertilizer and maintenanceVegetative cov", "Amount (Rs": "127,400.00" }, "geometry": { "type": "Point", "coordinates": [ 80.872972, 7.082263 ] } },
{ "type": "Feature", "properties": { "No": 5, "GND No.": "516B", "Descriptio": "Kovil Oya", "N": 7.093577, "E": 80.870517, "Observatio": "During the rainy season when too much water flows, Bank erosion occurs", "Descript_1": "Vegetative cover improving (1.5m-2.0m wide) with Areca nut seedlings @ 1.5m spacing in two rows, Beetle creeper VP @ 3m spacing in a single row, Green gram as a cover crop including applying of compost manure, NPK fertilizer and maintenanceVegetative cov", "Amount (Rs": "127,400.00" }, "geometry": { "type": "Point", "coordinates": [ 80.870517, 7.093577 ] } },
{ "type": "Feature", "properties": { "No": 6, "GND No.": "516C", "Descriptio": "Halmee Kandura", "N": 7.074022, "E": 80.878283, "Observatio": "Spill canal from Halmee Lake", "Descript_1": "Vegetative cover improving (1.5m-2.0m wide) with Areca nut seedlings @ 1.5m spacing in two rows, Beetle creeper VP @ 3m spacing in a single row, Green gram as a cover crop including applying of compost manure, NPK fertilizer and maintenanceVegetative cov", "Amount (Rs": "127,400.00" }, "geometry": { "type": "Point", "coordinates": [ 80.878283, 7.074022 ] } },
{ "type": "Feature", "properties": { "No": 7, "GND No.": "516D", "Descriptio": "Mahapathana Ela", "N": 7.06884, "E": 80.877083, "Observatio": "During the rainy season when too much water flows, Bank erosion occurs", "Descript_1": "Vegetative cover improving (1.5m-2.0m wide) with Areca nut seedlings @ 1.5m spacing in two rows, Beetle creeper VP @ 3m spacing in a single row, Green gram as a cover crop including applying of compost manure, NPK fertilizer and maintenanceVegetative cov", "Amount (Rs": "90,400.00" }, "geometry": { "type": "Point", "coordinates": [ 80.877083, 7.06884 ] } },
{ "type": "Feature", "properties": { "No": 8, "GND No.": "516D", "Descriptio": "Ma Ussakele - Yakkatava Oya", "N": 7.06082, "E": 80.87521, "Observatio": "During the rainy season when too much water flows, Bank erosion occurs", "Descript_1": "Vegetative cover improving (1.5m-2.0m wide) with Areca nut seedlings @ 1.5m spacing in two rows, Beetle creeper VP @ 3m spacing in a single row, Green gram as a cover crop including applying of compost manure, NPK fertilizer and maintenanceVegetative cov", "Amount (Rs": "254,800.00" }, "geometry": { "type": "Point", "coordinates": [ 80.87521, 7.06082 ] } },
{ "type": "Feature", "properties": { "No": 9, "GND No.": "516D", "Descriptio": "Ma Ussakele Upper Division Ela", "N": 7.06288, "E": 80.875558, "Observatio": "During the rainy season when too much water flows, Bank erosion occurs", "Descript_1": "Vegetative cover improving (1.5m-2.0m wide) with Areca nut seedlings @ 1.5m spacing in two rows, Beetle creeper VP @ 3m spacing in a single row, Green gram as a cover crop including applying of compost manure, NPK fertilizer and maintenanceVegetative cov", "Amount (Rs": "90,400.00" }, "geometry": { "type": "Point", "coordinates": [ 80.875558, 7.06288 ] } }
]
}
