{
"type": "FeatureCollection",
"name": "SWC_ON",
"crs": { "type": "name", "properties": { "name": "urn:ogc:def:crs:OGC:1.3:CRS84" } },
"features": [
{ "type": "Feature", "properties": { "No.": 5, "GN Divisio": 1133, "GN Divis_1": "Pitawala", "Key Activi": "1. Soil conservation practices - C.G. Division  (40d-70d)", "Priority b": 1, "N": 7.156825, "E": 80.691582, "Quantity": "8 ha", "Proposed m": "Live fencing/SALT and/or stone terracing/lock and spills, as applied", "Uniti Cost": "250.00 m-1", "Total Cost": "2,000,000.00", "Contributi": "Labour and other basic services by the Local community", "Time frame": "0.5 Years", "photopath": "https://raw.githubusercontent.com/MWS003-GIS/MWS003-GIS.github.io/main/IWWRMP/Data/EXD/200_photo/MWS_128/Lands_Tea_and_Pepper_Cultivation.jpg" }, "geometry": { "type": "Point", "coordinates": [ 80.691582, 7.156825 ] } },
{ "type": "Feature", "properties": { "No.": 6, "GN Divisio": 1133, "GN Divis_1": "Pitawala", "Key Activi": "2. Soil conservation practices - Levelan Watta  (50d-60d)", "Priority b": 5, "N": 7.149455, "E": 80.687256, "Quantity": "50 ha", "Proposed m": "Live fencing/SALT and/or stone terracing/lock and spills, as applied", "Uniti Cost": "250.00 m-1", "Total Cost": "3,125,000.00", "Contributi": "Labour and other basic services by the Local community", "Time frame": "1.5 Years", "photopath": "https://raw.githubusercontent.com/MWS003-GIS/MWS003-GIS.github.io/main/IWWRMP/Data/EXD/200_photo/MWS_128/Lands_Tea_Vegetable_Cultivation_Levallon_Estate.jpg" }, "geometry": { "type": "Point", "coordinates": [ 80.687256, 7.149455 ] } },
{ "type": "Feature", "properties": { "No.": 4, "GN Divisio": 1140, "GN Divis_1": "Thumpelawaka", "Key Activi": "1. Soil conservation practices) - Badrawathi Temple (45d-65d)", "Priority b": 1, "N": 7.177851, "E": 80.670614, "Quantity": "1 ha", "Proposed m": "Live fencing/SALT and/or stone terracing/lock and spills, as applied", "Uniti Cost": "250.00 m-1", "Total Cost": "250,000.00", "Contributi": "Labour and other basic services by the Local community", "Time frame": "0.25 Years", "photopath": "https://raw.githubusercontent.com/MWS003-GIS/MWS003-GIS.github.io/main/IWWRMP/Data/EXD/200_photo/MWS_128/Soil_Conservation_Badrawathi_Temple.jpg" }, "geometry": { "type": "Point", "coordinates": [ 80.670614, 7.177851 ] } }
]
}
