{
"type": "FeatureCollection",
"name": "SWC_ON",
"crs": { "type": "name", "properties": { "name": "urn:ogc:def:crs:OGC:1.3:CRS84" } },
"features": [
{ "type": "Feature", "properties": { "No.": 1, "GND No.": "468I", "GND Name": "Kikiliyamana", "Key Activities proposed for Soil and Water conservation": "1. Soil conservation practices -  Cultivating lands in slopy area of the 3rd mile post  (50°-60°)", "Priority based on Soil Erosion Hazard": 5, "N": 6.99532, "E": 80.714418, "Quantity": "18 ha", "Proposed measure/s": "1. Live fencing/SALT  - 12000 m/ 2. Lock and spills - 4000 m/ 3. Stone terracing - 2000 m/ 4. Agronomic practices should be adapted at optimum level (conservation tillage, crop rotation and diversification, cover crops, mulching, contour farming, windbre", "Uniti_Cost": "250.00 m-1/400.00 m-1/ 2500.00 m-1", "Total_Cost": 19600000, "Contribution (Local Community, LA, and the project)": "Labour and other basic services by the Local community", "Time frame for the implementation": "0.25 Years", "photopath": "https://raw.githubusercontent.com/MWS003-GIS/MWS003-GIS.github.io/main/IWWRMP/Data/EXD/200_photo/MWS_165_2/Soil conservation.jpg" }, "geometry": { "type": "Point", "coordinates": [ 80.714418, 6.99532 ] } }
]
}
