{
"type": "FeatureCollection",
"name": "Table 6_22",
"crs": { "type": "name", "properties": { "name": "urn:ogc:def:crs:OGC:1.3:CRS84" } },
"features": [
{ "type": "Feature", "properties": { "No": 1, "GND No.": "504 A", "Descriptio": "Kurunduoya Start", "N": 7.056677, "E": 80.854615, "Observatio": "During the rainy season when too much water flows, Bank erosion occurs", "Descript_1": "Vegetative cover improving (1.5m-2.0m wide) with Areca nut seedlings @ 1.5m spacing in two rows, Beetle creeper VP @ 3m spacing in a single row, Green gram as a cover crop including applying of compost manure, NPK fertilizer and maintenance", "Amount (Rs": "172,175.00" }, "geometry": { "type": "Point", "coordinates": [ 80.854615, 7.056677 ] } },
{ "type": "Feature", "properties": { "No": 2, "GND No.": "504 A", "Descriptio": "Galpotta Pathana Stream", "N": 7.052622, "E": 80.86358, "Observatio": "During the rainy season when too much water flows, Bank erosion occurs", "Descript_1": "Vegetative cover improving (1.5m-2.0m wide) with Areca nut seedlings @ 1.5m spacing in two rows, Beetle creeper VP @ 3m spacing in a single row, Green gram as a cover crop including applying of compost manure, NPK fertilizer and maintenance", "Amount (Rs": "219,175.00" }, "geometry": { "type": "Point", "coordinates": [ 80.86358, 7.052622 ] } },
{ "type": "Feature", "properties": { "No": 3, "GND No.": "504 B", "Descriptio": "Kurundu Oya", "N": 7.06437, "E": 80.840366, "Observatio": "Garbage is dumped in to the Kurundu Oya near the town of High forest, The water is polluted. During the rainy season when too much water flows, Bank erosion occurs", "Descript_1": "Vegetative cover improving (1.5m-2.0m wide) with Areca nut seedlings @ 1.5m spacing in two rows, Beetle creeper VP @ 3m spacing in a single row, Green gram as a cover crop including applying of compost manure, NPK fertilizer and maintenance", "Amount (Rs": "172,175.00" }, "geometry": { "type": "Point", "coordinates": [ 80.840366, 7.06437 ] } },
{ "type": "Feature", "properties": { "No": 4, "GND No.": "504 B", "Descriptio": "Stream near No. 14", "N": 7.057693, "E": 80.844145, "Observatio": "During the rainy season when too much water flows, Bank erosion occurs", "Descript_1": "Vegetative cover improving (1.5m-2.0m wide) with Areca nut seedlings @ 1.5m spacing in two rows, Beetle creeper VP @ 3m spacing in a single row, Green gram as a cover crop including applying of compost manure, NPK fertilizer and maintenance        Vegeta", "Amount (Rs": "172,175.00" }, "geometry": { "type": "Point", "coordinates": [ 80.844145, 7.057693 ] } },
{ "type": "Feature", "properties": { "No": 5, "GND No.": "504 D", "Descriptio": "3 A Kandura", "N": 7.05224, "E": 80.82748, "Observatio": "During the rainy season when too much water flows, Bank erosion occurs", "Descript_1": "Vegetative cover improving (1.5m-2.0m wide) with Areca nut seedlings @ 1.5m spacing in two rows, Beetle creeper VP @ 3m spacing in a single row, Green gram as a cover crop including applying of compost manure, NPK fertilizer and maintenance          Vege", "Amount (Rs": "218,062.50" }, "geometry": { "type": "Point", "coordinates": [ 80.82748, 7.05224 ] } },
{ "type": "Feature", "properties": { "No": 6, "GND No.": "533 I", "Descriptio": "Kalukele Ela ( Located in Reserve)", "N": 7.042231, "E": 80.829634, "Observatio": "During the rainy season when too much water flows, Bank erosion occurs", "Descript_1": "Vegetative cover improving (1.5m-2.0m wide) with Areca nut seedlings @ 1.5m spacing in two rows, Beetle creeper VP @ 3m spacing in a single row, Green gram as a cover crop including applying of compost manure, NPK fertilizer and maintenance", "Amount (Rs": "263,950.00" }, "geometry": { "type": "Point", "coordinates": [ 80.829634, 7.042231 ] } }
]
}
