{
"type": "FeatureCollection",
"name": "Table 6_20",
"crs": { "type": "name", "properties": { "name": "urn:ogc:def:crs:OGC:1.3:CRS84" } },
"features": [
{ "type": "Feature", "properties": { "No.": 1, "GN Divisio": "504 A", "GN Divis_1": "Binganthalawa", "Non-point": "There could be water pollution as caused by human waste", "N or X": 7.056918, "E or Y": 80.854227, "Number of": "Bromli - Common Toilets 10; Utkote - Common Toilets 15; Kahawaththa - Common Toilets 10; Loriston - Common Toilets 10", "Point sour": "-", "Add. N or": "-", "Add. E or": "-", "Recommende": "-", "Unit Cost": "-", "Total Cost": "-", "Contributi": "-", "Time frame": "-" }, "geometry": { "type": "Point", "coordinates": [ 80.854227, 7.056918 ] } },
{ "type": "Feature", "properties": { "No.": 2, "GN Divisio": "504 B", "GN Divis_1": "High forest", "Non-point": "There could be water pollution as caused by human waste", "N or X": 7.059834, "E or Y": 80.842565, "Number of": "Block No. 03 - 10", "Point sour": "-", "Add. N or": "-", "Add. E or": "-", "Recommende": "-", "Unit Cost": "-", "Total Cost": "-", "Contributi": "-", "Time frame": "-" }, "geometry": { "type": "Point", "coordinates": [ 80.842565, 7.059834 ] } },
{ "type": "Feature", "properties": { "No.": 3, "GN Divisio": "504 B", "GN Divis_1": "High forest", "Non-point": "Disposal of garbage to residential area and Kurundu Oya", "N or X": 7.059834, "E or Y": 80.842565, "Number of": "-", "Point sour": "-", "Add. N or": "-", "Add. E or": "-", "Recommende": "Preparing a separate place in home gardens for disposing household waste\nAwareness program on how to disposal household waste properly and converting them to usable products such as compost\nFacilitating garbage collection", "Unit Cost": "-", "Total Cost": "50,000.00", "Contributi": "Local/Central governments", "Time frame": "0.5 Years" }, "geometry": { "type": "Point", "coordinates": [ 80.842565, 7.059834 ] } },
{ "type": "Feature", "properties": { "No.": 4, "GN Divisio": "504 D", "GN Divis_1": "High forest Watta", "Non-point": "Improper disposal of domestic waste - High forest Watta", "N or X": 7.05764, "E or Y": 80.829465, "Number of": "-", "Point sour": "-", "Add. N or": "-", "Add. E or": "-", "Recommende": "Preparing a separate place in home gardens for disposing household waste\nAwareness program on how to disposal household waste properly and converting them to usable products such as compost\nFacilitating garbage collection", "Unit Cost": "-", "Total Cost": "50,000.00", "Contributi": "Local/Central governments", "Time frame": "0.5 Years" }, "geometry": { "type": "Point", "coordinates": [ 80.829465, 7.05764 ] } },
{ "type": "Feature", "properties": { "No.": 5, "GN Divisio": "533 I", "GN Divis_1": "Mahakudugala", "Non-point": "There could be water pollution as caused by human waste", "N or X": 7.033546, "E or Y": 80.825768, "Number of": "Mahakudugala (Lower Section) - 20", "Point sour": "-", "Add. N or": "-", "Add. E or": "-", "Recommende": "-", "Unit Cost": "-", "Total Cost": "-", "Contributi": "-", "Time frame": "-" }, "geometry": { "type": "Point", "coordinates": [ 80.825768, 7.033546 ] } },
{ "type": "Feature", "properties": { "No.": 6, "GN Divisio": "533 I", "GN Divis_1": "Mahakudugala", "Non-point": "Improper disposal of domestic waste - High forest Watta", "N or X": 7.033546, "E or Y": 80.825768, "Number of": "-", "Point sour": "-", "Add. N or": "-", "Add. E or": "-", "Recommende": "Preparing a separate place in home gardens for disposing household waste\nAwareness program on how to disposal household waste properly and converting them to usable products such as compost\nFacilitating garbage collection", "Unit Cost": "-", "Total Cost": "50,000.00", "Contributi": "Local/Central governments", "Time frame": "0.5 Years" }, "geometry": { "type": "Point", "coordinates": [ 80.825768, 7.033546 ] } }
]
}
