{
  "type": "FeatureCollection",
  "name": "MT",
  "features": [
    {"type":"Feature","properties":{"Name_of_Tank":"Pond in seed potato farm","Name_of_Custodian":"DAD","N":6.929358,"E":80.776328,"Remarks":"This is a newly proposed tank. It is a pond at present and beneficiaries request for a tank.\n","photopath":"https://raw.githubusercontent.com/MWS003-GIS/MWS003-GIS.github.io/main/IWWRMP/Data/EXD/200_photo/MWS_163/IMG_20260116_115715 Goverment seed production farm proposed Lake.jpg"},"geometry":{"type":"Point","coordinates":[80.776328,6.929358]}}
  ]
}