{
"type": "FeatureCollection",
"name": "SWC_OFF",
"crs": { "type": "name", "properties": { "name": "urn:ogc:def:crs:OGC:1.3:CRS84" } },
"features": [
{ "type": "Feature", "properties": { "No.": 5, "GN Divisio": 1143, "GN Divis_1": "Thundeniya", "Key Activi": "1. Construction of a Retaining Wall", "Priority b": 4, "N": 7.16153, "E": 80.597875, "Quantity": "10 m long and 3.0 m  hight", "Proposed m": "Retaining Wall (Concrete)", "Total Cost": "1,171,500.00", "Contributi": "By the project", "Time frame": "0.25 Years", "photopath": "-" }, "geometry": { "type": "Point", "coordinates": [ 80.597875, 7.16153 ] } },
{ "type": "Feature", "properties": { "No.": 6, "GN Divisio": 1143, "GN Divis_1": "Thundeniya", "Key Activi": "2. Construction of a Retaining Wall", "Priority b": 5, "N": 7.161772, "E": 80.602869, "Quantity": "10 m long and 3.0 m  hight", "Proposed m": "Retaining Wall (Concrete)", "Total Cost": "1,171,500.00", "Contributi": "By the project", "Time frame": "0.25 Years", "photopath": "-" }, "geometry": { "type": "Point", "coordinates": [ 80.602869, 7.161772 ] } },
{ "type": "Feature", "properties": { "No.": 13, "GN Divisio": 1146, "GN Divis_1": "Lagumdeniya", "Key Activi": "1. Construction of a Retaining Wall", "Priority b": 1, "N": 7.161902, "E": 80.628818, "Quantity": "25 m long and 3 m high", "Proposed m": "Retaining Wall (Concrete)", "Total Cost": "2,909,500.00", "Contributi": "By the project", "Time frame": "0.25 Years", "photopath": "-" }, "geometry": { "type": "Point", "coordinates": [ 80.628818, 7.161902 ] } }
]
}
