{
"type": "FeatureCollection",
"name": "Table 6_21",
"crs": { "type": "name", "properties": { "name": "urn:ogc:def:crs:OGC:1.3:CRS84" } },
"features": [
{ "type": "Feature", "properties": { "No": 1, "GND No.": "526C", "Name of Ir": "Kande Ela", "N": 7.042738, "E": 80.883891, "Observatio": "The total length of the canal is 3.5km, 1.0km section are concreted, Another 2.5km section should be concreted, Command area 250.0 acres", "Descriptio": "Canals reservation protection by concrete lining  for 100m and  125mm thick , 0.5m  wide  and 0.4m high canal -double banking.Stream / canal  reservation protection by earthfilling of  strip   of 1.5m to 2m wide  and average Depth of 0.5m, Turfing to new", "Amount": "2,820,000.00" }, "geometry": { "type": "Point", "coordinates": [ 80.883891, 7.042738 ] } }
]
}
