{
"type": "FeatureCollection",
"name": "Landslides",
"crs": { "type": "name", "properties": { "name": "urn:ogc:def:crs:OGC:1.3:CRS84" } },
"features": [
{ "type": "Feature", "properties": { "No.": 23, "GN Division No.": "458", "GN Division": "Ranwanthalawa", "Landslides": "1. Landsliding - Near the Ranwanthalawa Makadura Canal", "N": 7.066753, "E": 80.617889, "NBRO Recommendation N/A": "NBRO is aware", "Proposed Measures": "Follow recommendations of NBRO having consulted. Relocating is needed. Lands have been provided.", "Unnamed: 8": null, "photopath": "https://raw.githubusercontent.com/MWS003-GIS/MWS003-GIS.github.io/main/IWWRMP/Data/EXD/200_photo/MWS_179_2/Landslide Area.jpg" }, "geometry": { "type": "Point", "coordinates": [ 80.617889, 7.066753 ] } },
{ "type": "Feature", "properties": { "No.": 26, "GN Division No.": "459B", "GN Division": "Kotagepitiya North", "Landslides": "1. Collapsing boulders", "N": 7.077058, "E": 80.614619, "NBRO Recommendation N/A": "Needs NBRO concern", "Proposed Measures": "Since this road is a secondary route that passes through a very sparsely populated area, it is not considered necessary to undertake any development work at this location. Some retaining structires will also be needed.", "Unnamed: 8": null, "photopath": "https://raw.githubusercontent.com/MWS003-GIS/MWS003-GIS.github.io/main/IWWRMP/Data/EXD/200_photo/MWS_179_2/Kithulbadda - Davatagas Road - Landslide Area.jpg" }, "geometry": { "type": "Point", "coordinates": [ 80.614619, 7.077058 ] } }
]
}
