{
"type": "FeatureCollection",
"name": "SR",
"crs": { "type": "name", "properties": { "name": "urn:ogc:def:crs:OGC:1.3:CRS84" } },
"features": [
{ "type": "Feature", "properties": { "No": 1, "GND No.": "459", "Scheme": "Canal near Mrs. Manoja's house of Kithulbedda", "N": 7.072763, "E": 80.602233, "Observation": "During the rainy season when too much water flows, Bank erosion occurs", "Description": "Vegetative cover improving around the river bank with Areca nut seedling in 1.5m x 1.5m grid, Kumbuk/ Mee/ Godapara/ Kaduru/ Aththikka/ Wal Del/ Kekuna/ randomly mixed seedlings and planting at 3.5m x 3.5 m grid interval\n\nReplanting bamboo species around", "Amount (Rs.)": 713900, "photopath": "https://raw.githubusercontent.com/MWS003-GIS/MWS003-GIS.github.io/main/IWWRMP/Data/EXD/200_photo/MWS_179_2/Kithulbadda Stream.jpg" }, "geometry": { "type": "Point", "coordinates": [ 80.602233, 7.072763 ] } },
{ "type": "Feature", "properties": { "No": 2, "GND No.": "459", "Scheme": "Rukaththana canal", "N": 7.076506, "E": 80.601259, "Observation": "During the rainy season when too much water flows, Bank erosion occurs", "Description": "Vegetative cover improving around the river bank with Areca nut seedling in 1.5m x 1.5m grid, Kumbuk/ Mee/ Godapara/ Kaduru/ Aththikka/ Wal Del/ Kekuna/ randomly mixed seedlings and planting at 3.5m x 3.5 m grid interval\n\nReplanting bamboo species around", "Amount (Rs.)": 768350, "photopath": "https://raw.githubusercontent.com/MWS003-GIS/MWS003-GIS.github.io/main/IWWRMP/Data/EXD/200_photo/MWS_179_2/Rukattana Canal 2.jpg" }, "geometry": { "type": "Point", "coordinates": [ 80.601259, 7.076506 ] } },
{ "type": "Feature", "properties": { "No": 3, "GND No.": "459A", "Scheme": "Ketena canal at the Maippala area", "N": 7.072383, "E": 80.618425, "Observation": "During the rainy season when too much water flows, Bank erosion occurs", "Description": "Vegetative cover improving around the river bank with Areca nut seedling in 1.5m x 1.5m grid, Kumbuk/ Mee/ Godapara/ Kaduru/ Aththikka/ Wal Del/ Kekuna/ randomly mixed seedlings and planting at 3.5m x 3.5 m grid interval\n\nReplanting bamboo species around", "Amount (Rs.)": 695750, "photopath": "https://raw.githubusercontent.com/MWS003-GIS/MWS003-GIS.github.io/main/IWWRMP/Data/EXD/200_photo/MWS_179_2/Ketana stream.jpg" }, "geometry": { "type": "Point", "coordinates": [ 80.618425, 7.072383 ] } }
]
}
