{
"type": "FeatureCollection",
"name": "WSP",
"crs": { "type": "name", "properties": { "name": "urn:ogc:def:crs:OGC:1.3:CRS84" } },
"features": [
{ "type": "Feature", "properties": { "No": 1.0, "MWS_ID": "107-2", "GND No.": 667.0, "Name of Sp": "Gedarakumbura Well", "N": 7.31717, "E": "80.66657", "Observatio": "The well, which is 1.35m  in diameter, has  used rings. though the pavement around the well is concreted,currently it is damaged used for drinking and bathing  located in a paddy field", "Descriptio": "1:3:6 (40mm) concrete manual mix (volume batching) \n\nMiscellaneous\n\nContigencies (10%)\n\n", "Amount (Rs": "6,380.00", "photopath": "https://raw.githubusercontent.com/MWS003-GIS/MWS003-GIS.github.io/main/IWWRMP/Data/EXD/200_photo/MWS_107_2/IMG_20250121_113204 Gedara kumbura well.jpg" }, "geometry": { "type": "Point", "coordinates": [ 80.66657, 7.31717 ] } },
{ "type": "Feature", "properties": { "No": 2.0, "MWS_ID": "107-2", "GND No.": 667.0, "Name of Sp": "Palperu anga Well", "N": 7.31652, "E": "80.66711", "Observatio": "The  well is constructed (2.1m x 2.1m x 2.5 m, L*W*H) though the pavement around the well is concreted,currently it is damaged it is close to the paddy field.used for drinking and bathing", "Descriptio": "1:3:6 (40mm) concrete manual mix (volume batching) \n\n Fabricating & fixing security weld mesh in open\ntype buildings in GI weld mesh 50mm x 50mm \nSWG 10, welded on 40mm x 40mm x 5mm \nangle frame complete with application of two \ncoats enamel paint over t", "Amount (Rs": "84,700.00", "photopath": "https://raw.githubusercontent.com/MWS003-GIS/MWS003-GIS.github.io/main/IWWRMP/Data/EXD/200_photo/MWS_107_2/IMG_20250121_115806 palperu anga well.jpg" }, "geometry": { "type": "Point", "coordinates": [ 80.66711, 7.31652 ] } },
{ "type": "Feature", "properties": { "No": 3.0, "MWS_ID": "107-2", "GND No.": 667.0, "Name of Sp": "Buanga pansale Well", "N": 7.31611, "E": "80.66283", "Observatio": "The  well is constructed (2.1m x 2.1m x 2.5 m, L*W*H)it is close to the paddy field.used for drinking and bathing", "Descriptio": "1:3:6 (40mm) concrete manual mix (volume batching) \n\nMiscellaneous\n\nContigencies (10%)\n\n", "Amount (Rs": "6,160.00", "photopath": "-" }, "geometry": { "type": "Point", "coordinates": [ 80.66283, 7.31611 ] } },
{ "type": "Feature", "properties": { "No": 4.0, "MWS_ID": "107-2", "GND No.": 666.0, "Name of Sp": "Balathota canal", "N": 7.32486, "E": "80.66253", "Observatio": "During the rainy season when too much water flows, Bank erosion occurs", "Descriptio": "Vegetative cover improving around structures (5m x 10m) with Areca nut seedling in 1.5m x \n1.5m grid, Kumbuk/ Mee/ Godapara/ Kaduru/ Aththikka/ Wal Del/ Kekuna/ randomly mixed \nseedlings and planting at 3.5m x 3.5 m grid interval\n\nReplanting?bamboo?s", "Amount (Rs": "62,920.00", "photopath": "https://raw.githubusercontent.com/MWS003-GIS/MWS003-GIS.github.io/main/IWWRMP/Data/EXD/200_photo/MWS_107_2/IMG_20250116_094150  Balathota canal.jpg" }, "geometry": { "type": "Point", "coordinates": [ 80.66253, 7.32486 ] } }
]
}
