{
"type": "FeatureCollection",
"name": "Table 6-9",
"crs": { "type": "name", "properties": { "name": "urn:ogc:def:crs:OGC:1.3:CRS84" } },
"features": [
{ "type": "Feature", "properties": { "No.": 1, "GN Division No.": 988, "GN Division": "Sinharagama", "Non-point sources of pollution": "Addition of beer tins, plastic, polythene etc.", "N or X": 7.251845, "E or Y": 80.71205, "Point sources of pollution": null, "Recommended water quality improvement measures": "Awareness programme on proper disposal of household waste", "Unit Cost (Rs.)": null, "Total Cost (Rs.)": "50,000.00", "Contributions (Local Community, LA, Project)": "Local Government", "Time frame for the implementation": "0.5 Years" }, "geometry": { "type": "Point", "coordinates": [ 80.71205, 7.251845 ] } },
{ "type": "Feature", "properties": { "No.": 2, "GN Division No.": 1001, "GN Division": "Haragama", "Non-point sources of pollution": "Addition of household wastes - Anuragama Main Road", "N or X": 7.245923, "E or Y": 80.72964, "Point sources of pollution": null, "Recommended water quality improvement measures": "Awareness programme on proper disposal of household waste", "Unit Cost (Rs.)": null, "Total Cost (Rs.)": "50,000.00", "Contributions (Local Community, LA, Project)": "Local Government", "Time frame for the implementation": "0.5 Years" }, "geometry": { "type": "Point", "coordinates": [ 80.72964, 7.245923 ] } },
{ "type": "Feature", "properties": { "No.": 3, "GN Division No.": 1001, "GN Division": "Haragama", "Non-point sources of pollution": "-", "N or X": 7.241048, "E or Y": 80.72779, "Point sources of pollution": null, "Recommended water quality improvement measures": "Facilitate collection of waste by the local government with a proper schedule", "Unit Cost (Rs.)": null, "Total Cost (Rs.)": null, "Contributions (Local Community, LA, Project)": null, "Time frame for the implementation": null }, "geometry": { "type": "Point", "coordinates": [ 80.72779, 7.241048 ] } },
{ "type": "Feature", "properties": { "No.": 4, "GN Division No.": 1002, "GN Division": "Uda Mailapitiya North", "Non-point sources of pollution": "Accumulation of household waste in different places", "N or X": null, "E or Y": null, "Point sources of pollution": null, "Recommended water quality improvement measures": "Awareness programme on proper disposal of household waste\nFacilitate collection of waste by the local government with a proper schedule", "Unit Cost (Rs.)": null, "Total Cost (Rs.)": "50,000.00", "Contributions (Local Community, LA, Project)": "Local Government", "Time frame for the implementation": "0.5 Years" }, "geometry": null }
]
}
