{
"type": "FeatureCollection",
"name": "Table 6_3",
"crs": { "type": "name", "properties": { "name": "urn:ogc:def:crs:OGC:1.3:CRS84" } },
"features": [
{ "type": "Feature", "properties": { "Tank name": "Garandi Wewa", "Ownership": "DAD", "N": 7.03053, "E": 80.87932, "Remarks": "Clearing of Lake, Water Pollution Prevention and Inland fish farming" }, "geometry": { "type": "Point", "coordinates": [ 80.87932, 7.03053 ] } },
{ "type": "Feature", "properties": { "Tank name": "Kuundalu  Wewa", "Ownership": "DAD", "N": 7.03726, "E": 80.88071, "Remarks": "Clearing of Lake, Water Pollution Prevention and Inland fish farming" }, "geometry": { "type": "Point", "coordinates": [ 80.88071, 7.03726 ] } },
{ "type": "Feature", "properties": { "Tank name": "Theppu Kulama Wewa", "Ownership": "DAD", "N": 7.006735, "E": 80.878417, "Remarks": "Water Pollution Prevention and Preparing a maintenance system" }, "geometry": { "type": "Point", "coordinates": [ 80.878417, 7.006735 ] } }
]
}
