{
"type": "FeatureCollection",
"name": "MT",
"crs": { "type": "name", "properties": { "name": "urn:ogc:def:crs:OGC:1.3:CRS84" } },
"features": [
{ "type": "Feature", "properties": { "Tank name": "Garandi Wewa", "Ownership": "DAD", "Location N": 7.03053, "Location E": 80.87932, "Remarks": "Clearing of Lake, Water Pollution Prevention and Inland fish farming", "photopath": "https://raw.githubusercontent.com/MWS003-GIS/MWS003-GIS.github.io/main/IWWRMP/Data/EXD/200_photo/MWS_023/Garadi lake.jpg" }, "geometry": { "type": "Point", "coordinates": [ 80.87932, 7.03053 ] } },
{ "type": "Feature", "properties": { "Tank name": "Kuundalu  Wewa", "Ownership": "DAD", "Location N": 7.03726, "Location E": 80.88071, "Remarks": "Clearing of Lake, Water Pollution Prevention and Inland fish farming", "photopath": "https://raw.githubusercontent.com/MWS003-GIS/MWS003-GIS.github.io/main/IWWRMP/Data/EXD/200_photo/MWS_023/Kuudalu lake.jpg" }, "geometry": { "type": "Point", "coordinates": [ 80.88071, 7.03726 ] } },
{ "type": "Feature", "properties": { "Tank name": "Theppu Kulama Wewa", "Ownership": "DAD", "Location N": 7.006735, "Location E": 80.878417, "Remarks": "Water Pollution Prevention and Preparing a maintenance system", "photopath": "-" }, "geometry": { "type": "Point", "coordinates": [ 80.878417, 7.006735 ] } }
]
}
