{
"type": "FeatureCollection",
"name": "MI",
"crs": { "type": "name", "properties": { "name": "urn:ogc:def:crs:OGC:1.3:CRS84" } },
"features": [
{ "type": "Feature", "properties": { "No": 1, "GND No.": "460A", "Scheme": "Panwatta Meda canal", "N": 7.073527, "E": 80.545571, "Observation": "Existing Earthen canal, some places are in a very dilapidated condition.     Water from this canal is used to grow paddy on an area of about 15 acres", "Description": "Canal reservation protection by concrete lining  For  100mm thick , 0.3m  wide  and 0.3m high canal -double banking\n\nStream / canal  reservation protection by earth filling of  strip   of 1.5m to 2m wide  and average Depth of 0.5m\n\nVegetative cover impro", "Amount (Rs.)": 770000, "photopath": "https://raw.githubusercontent.com/MWS003-GIS/MWS003-GIS.github.io/main/IWWRMP/Data/EXD/200_photo/MWS_177/-" }, "geometry": { "type": "Point", "coordinates": [ 80.545571, 7.073527 ] } },
{ "type": "Feature", "properties": { "No": 2, "GND No.": "460A", "Scheme": "Panwatta Pita Ela", "N": 7.073522, "E": 80.545558, "Observation": "Existing Earthen canal, some places are in a very dilapidated condition.     Water from this canal is used to grow paddy on an area of about 10 acres", "Description": "Construction of 1.5m high 1:3:6 (40mm) cement concrete Retaining Wall \n\nVegetative cover improving for narrow strips (1.5m-2.0m wide) with Arecanut seedlings at 1.5m spacing in 2 rows, Betel plants VP at 3m spacing in 1 row, Green gram as a cover crop\n\nM", "Amount (Rs.)": 2035000, "photopath": "https://raw.githubusercontent.com/MWS003-GIS/MWS003-GIS.github.io/main/IWWRMP/Data/EXD/200_photo/MWS_177/-" }, "geometry": { "type": "Point", "coordinates": [ 80.545558, 7.073522 ] } }
]
}
