{
"type": "FeatureCollection",
"name": "MT",
"crs": { "type": "name", "properties": { "name": "urn:ogc:def:crs:OGC:1.3:CRS84" } },
"features": [
{ "type": "Feature", "properties": { "No": 1.0, "MWS_ID": 104.0, "Name of Ta": "Pahala Bogahapitiya Reservoir", "Custodians": "DAD", "N": 7.288356, "E": 80.708819, "Remarks?": "Desilting, Construction of a Head wall type sluice with CO spillway, Bund improvements proposed", "photopath": "-" }, "geometry": { "type": "Point", "coordinates": [ 80.708819, 7.288356 ] } },
{ "type": "Feature", "properties": { "No": 2.0, "MWS_ID": 104.0, "Name of Ta": "Ritigahawagura Pathaha", "Custodians": "DAD", "N": 7.304746, "E": 80.714479, "Remarks?": "Desilting, improvements to the bund, reconstruction of sluice proposed", "photopath": "-" }, "geometry": { "type": "Point", "coordinates": [ 80.714479, 7.304746 ] } },
{ "type": "Feature", "properties": { "No": 3.0, "MWS_ID": 104.0, "Name of Ta": "Kiramba Pathaha", "Custodians": "DAD", "N": 7.305754, "E": 80.716635, "Remarks?": "Desilting, improvements to the bund, reconstruction of sluice, repairs to the spillway, marking reservations and preventing bank erosions proposed", "photopath": "https://raw.githubusercontent.com/MWS003-GIS/MWS003-GIS.github.io/main/IWWRMP/Data/EXD/200_photo/MWS_104/Kiramba Pathaha 1.jpg" }, "geometry": { "type": "Point", "coordinates": [ 80.716635, 7.305754 ] } },
{ "type": "Feature", "properties": { "No": 4.0, "MWS_ID": 104.0, "Name of Ta": "Ankandura Pathaha", "Custodians": "DAD", "N": 7.289262, "E": 80.727234, "Remarks?": "Desilting, improvements to the bund, reconstruction of sluice proposed", "photopath": "-" }, "geometry": { "type": "Point", "coordinates": [ 80.727234, 7.289262 ] } },
{ "type": "Feature", "properties": { "No": 5.0, "MWS_ID": 104.0, "Name of Ta": "Aswedduma Pathaha", "Custodians": "DAD", "N": 7.304727, "E": 80.7081, "Remarks?": "Desilting, improvements to the bund, reconstruction of sluice, construction of a concrete canal proposed", "photopath": "https://raw.githubusercontent.com/MWS003-GIS/MWS003-GIS.github.io/main/IWWRMP/Data/EXD/200_photo/MWS_104/Aswedduma Pathaha.jpg" }, "geometry": { "type": "Point", "coordinates": [ 80.7081, 7.304727 ] } },
{ "type": "Feature", "properties": { "No": 6.0, "MWS_ID": 104.0, "Name of Ta": "Thalkotuwa Pathaha", "Custodians": "DAD", "N": 7.307183, "E": 80.704723, "Remarks?": "No tank visible at the moment. Restoration not encouraged.", "photopath": "https://raw.githubusercontent.com/MWS003-GIS/MWS003-GIS.github.io/main/IWWRMP/Data/EXD/200_photo/MWS_104/Thalkotuwa Pathaha.jpg" }, "geometry": { "type": "Point", "coordinates": [ 80.704723, 7.307183 ] } },
{ "type": "Feature", "properties": { "No": 7.0, "MWS_ID": 104.0, "Name of Ta": "Udakumbura Pathaha", "Custodians": "DAD", "N": 7.312909, "E": 80.701736, "Remarks?": "Desilting, improvements to the bund, reconstruction of sluice proposed", "photopath": "https://raw.githubusercontent.com/MWS003-GIS/MWS003-GIS.github.io/main/IWWRMP/Data/EXD/200_photo/MWS_104/Udakumbura Pathaha 1.jpg" }, "geometry": { "type": "Point", "coordinates": [ 80.701736, 7.312909 ] } },
{ "type": "Feature", "properties": { "No": 8.0, "MWS_ID": 104.0, "Name of Ta": "Kovilahinna Pathaha", "Custodians": "DAD", "N": 7.31006, "E": 80.702472, "Remarks?": "Tank is in a dilapidated condition and no restoration proposed", "photopath": "-" }, "geometry": { "type": "Point", "coordinates": [ 80.702472, 7.31006 ] } },
{ "type": "Feature", "properties": { "No": 9.0, "MWS_ID": 104.0, "Name of Ta": "Kumburegama Pathaha", "Custodians": "DAD", "N": 7.318723, "E": 80.706486, "Remarks?": "Desilting, improvements to the bund, reconstruction of sluice proposed", "photopath": "-" }, "geometry": { "type": "Point", "coordinates": [ 80.706486, 7.318723 ] } }
]
}
