{
"type": "FeatureCollection",
"name": "WP",
"crs": { "type": "name", "properties": { "name": "urn:ogc:def:crs:OGC:1.3:CRS84" } },
"features": [
{ "type": "Feature", "properties": { "No_": 2, "MWS_ID": "034-2", "GN_Divisio": "37E", "GN_Divis_1": "Yalagamuwa", "Non_point": "Potential to add human waste - Bothalapitiya", "N": 7.0501292, "E": 80.9537207, "No__of_Toi": 10, "Point_sour": "-", "Add__N": "-", "Add__E": "-", "Recommende": "-", "Unit_Cost": "-", "Total_Cost": "-", "Contributi": "-", "Time_frame": "-", "photopath": "-" }, "geometry": { "type": "Point", "coordinates": [ 80.9537207, 7.0501292 ] } }
]
}
