{
"type": "FeatureCollection",
"name": "SR",
"crs": { "type": "name", "properties": { "name": "urn:ogc:def:crs:OGC:1.3:CRS84" } },
"features": [
{ "type": "Feature", "properties": { "No_": 3, "GND_No_": "57", "Descriptio": "Godathenna", "N": 6.891331, "E": 80.989881, "Observatio": "It is in the form of a kandura.During the rainy season when too much water flows, Bank erosion occurs", "Descript_1": "Paving available stone in the river banks and Planting trees\n\nDry rubble packing (with locally found rubble, size over 225mm )-Along the river banks\n\nVegetative cover improving around the water source with Areca nut seedling in 1.5m x 1.5m grid, Kumbuk/", "Amount": 539000, "photopath": "https://raw.githubusercontent.com/MWS003-GIS/MWS003-GIS.github.io/main/IWWRMP/Data/EXD/200_photo/MWS_068/IMG_20251015_092952 Godathenna kandura.jpg" }, "geometry": { "type": "Point", "coordinates": [ 80.989881, 6.891331 ] } },
{ "type": "Feature", "properties": { "No_": 1, "GND_No_": "57A", "Descriptio": "Othalawa oya", "N": 6.893312, "E": 80.967639, "Observatio": "During the rainy season when too much water flows, Bank erosion occurs(Belongs to the South Bank GND)", "Descript_1": "Paving available stone in the river banks and Planting trees\n\nDry rubble packing (with locally found rubble, size over 225mm )-Along the river banks\n\nVegetative cover improving around the water source with Areca nut seedling in 1.5m x 1.5m grid, Kumbuk/", "Amount": 520300, "photopath": "https://raw.githubusercontent.com/MWS003-GIS/MWS003-GIS.github.io/main/IWWRMP/Data/EXD/200_photo/MWS_068/IMG_20251008_093737 Othalawa oya.jpg" }, "geometry": { "type": "Point", "coordinates": [ 80.967639, 6.893312 ] } },
{ "type": "Feature", "properties": { "No_": 4, "GND_No_": "57C", "Descriptio": "Bulathwel kandura", "N": 6.878293, "E": 80.964665, "Observatio": "During the rainy season when too much water flows, Bank erosion occurs", "Descript_1": "Paving available stone in the river banks and Planting trees\n\nDry rubble packing (with locally found rubble, size over 225mm )-Along the river banks\n\nVegetative cover improving around the water source with Areca nut seedling in 1.5m x 1.5m grid, Kumbuk/", "Amount": 636900, "photopath": null }, "geometry": { "type": "Point", "coordinates": [ 80.964665, 6.878293 ] } },
{ "type": "Feature", "properties": { "No_": 5, "GND_No_": "57C", "Descriptio": "Boragas Spring(Kandura)", "N": 6.879481, "E": 80.961799, "Observatio": "It is in the form of a kandura.During the rainy season when too much water flows, Bank erosion occurs", "Descript_1": "Paving available stone in the river banks and Planting trees\n\nDry rubble packing (with locally found rubble, size over 225mm )-Along the river banks\n\nVegetative cover improving around the water source with Areca nut seedling in 1.5m x 1.5m grid, Kumbuk/", "Amount": 539000, "photopath": "https://raw.githubusercontent.com/MWS003-GIS/MWS003-GIS.github.io/main/IWWRMP/Data/EXD/200_photo/MWS_068/IMG_20251014_104654 Boragas Reserve.jpg" }, "geometry": { "type": "Point", "coordinates": [ 80.961799, 6.879481 ] } },
{ "type": "Feature", "properties": { "No_": 2, "GND_No_": "57G", "Descriptio": "Bolerawa to Watawama kandura", "N": 6.882111, "E": 80.978883, "Observatio": "During the rainy season when too much water flows, Bank erosion occurs", "Descript_1": "Soil Excavation to drain water \n\nContingencies (10%)", "Amount": 33000, "photopath": "https://raw.githubusercontent.com/MWS003-GIS/MWS003-GIS.github.io/main/IWWRMP/Data/EXD/200_photo/MWS_068/IMG_20251009_094433Bolerawa kandura.jpg" }, "geometry": { "type": "Point", "coordinates": [ 80.978883, 6.882111 ] } }
]
}
