{
"type": "FeatureCollection",
"name": "Table 6_17",
"crs": { "type": "name", "properties": { "name": "urn:ogc:def:crs:OGC:1.3:CRS84" } },
"features": [
{ "type": "Feature", "properties": { "No": 1, "GND No.": "491/B", "Scheme": "Andiribedda tube well", "Problem to be addressed/Recommendation": "Supply and install complete manually operated pump and all accessories in working order to the existing tube well. Item allow", "N": 7.179369, "E": 80.8351, "Estimated Cost (LKR)": "600,000", "photopath": "-" }, "geometry": { "type": "Point", "coordinates": [ 80.8351, 7.179369 ] } },
{ "type": "Feature", "properties": { "No": 2, "GND No.": "491/B", "Scheme": "Andiribedda rainwater harvesting tanks. 15 numbers", "Problem to be addressed/Recommendation": "Supply all materials and labour necessary for complete construction of ferro cement storage tank of 35 cum - size internal 3m Dia x4m high. (@ 325000)", "N": 7.180059, "E": 80.83646, "Estimated Cost (LKR)": "4,875,000", "photopath": "-" }, "geometry": { "type": "Point", "coordinates": [ 80.83646, 7.180059 ] } }
]
}
