{
"type": "FeatureCollection",
"name": "DWS",
"crs": { "type": "name", "properties": { "name": "urn:ogc:def:crs:OGC:1.3:CRS84" } },
"features": [
{ "type": "Feature", "properties": { "GND_No_": 1067, "Name_of_th": "Lantern Hill forest reserve", "N": 7.145804, "E": 80.553197, "Observatio": "There are many springs and water is used privately.", "Descriptio": "Construction of a 1.2m Dia x 2.0m deep well\n\nExcavation in wells/pits in normal earth up to a depth of 1.0m including backfilling behind wall/ring and disposal of surplus earth, rate excluding shoring (for 1.2m Dia rings)\n\nExcavation in wells/pits in nor", "Amount__Rs": 2475000, "photopath": "https://raw.githubusercontent.com/MWS003-GIS/MWS003-GIS.github.io/main/IWWRMP/Data/EXD/200_photo/MWS_135/Water Catchment Area Conservation  - Springs at Lanternhill C area (6).jpg" }, "geometry": { "type": "Point", "coordinates": [ 80.553197, 7.145804 ] } }
]
}
