{
"type": "FeatureCollection",
"name": "Table 6_10",
"crs": { "type": "name", "properties": { "name": "urn:ogc:def:crs:OGC:1.3:CRS84" } },
"features": [
{ "type": "Feature", "properties": { "Tank name": "Bandiyawa wewa ", "Land ownership": "DAD", "N": 7.16407, "E": 80.81693, "Tentative Estimate (LKR)": "1,452,000.00", "photopath": "-" }, "geometry": { "type": "Point", "coordinates": [ 80.81693, 7.16407 ] } },
{ "type": "Feature", "properties": { "Tank name": "Goda Iluk wewa", "Land ownership": "DAD", "N": 7.168988, "E": 80.811382, "Tentative Estimate (LKR)": "1,188,000.00", "photopath": "-" }, "geometry": { "type": "Point", "coordinates": [ 80.811382, 7.168988 ] } },
{ "type": "Feature", "properties": { "Tank name": "Mee aththa wewa", "Land ownership": "DAD", "N": 7.1949, "E": 80.8077, "Tentative Estimate (LKR)": "600,000.00", "photopath": "https://raw.githubusercontent.com/MWS003-GIS/MWS003-GIS.github.io/main/IWWRMP/Data/EXD/200_photo/MWS_014/HK (04)5.jpg" }, "geometry": { "type": "Point", "coordinates": [ 80.8077, 7.1949 ] } },
{ "type": "Feature", "properties": { "Tank name": "Bodhigolla wewa", "Land ownership": "DAD", "N": 7.19791, "E": 80.79408, "Tentative Estimate (LKR)": "1, 176,000.00", "photopath": "https://raw.githubusercontent.com/MWS003-GIS/MWS003-GIS.github.io/main/IWWRMP/Data/EXD/200_photo/MWS_014/HK (04)1.jpg" }, "geometry": { "type": "Point", "coordinates": [ 80.79408, 7.19791 ] } },
{ "type": "Feature", "properties": { "Tank name": "Total", "Land ownership": "DAD", "N": 7.1949, "E": 80.8077, "Tentative Estimate (LKR)": "4,416,000.00", "photopath": "-" }, "geometry": { "type": "Point", "coordinates": [ 80.8077, 7.1949 ] } }
]
}
